[{"topic":"산소계표백제","label":"세탁기 투입구","detail":"세탁기 사용 설명서에 '표백제 투입량'과 '세탁물 종류'에 따른 권장 사용량이 제시되어 있다."},{"topic":"염소계표백제","label":"세탁실의 냄새","detail":"염소계표백제를 사용한 직후 발생하는 특유의 강한 냄새는 염소 가스(Cl₂)가 공기 중으로 방출되고 있다는 명확한 신호이다."},{"topic":"염소계표백제","label":"흰 옷의 변색 정도","detail":"표백 후 흰 옷이 지나치게 하얗거나, 특정 부분에서 누렇게 변색된 경우, 과도한 표백제 사용이나 잘못된 세탁 과정이 있었음을 의미한다."},{"topic":"베이킹소다세탁","label":"세탁물에서 나는 꿉꿉한 냄새","detail":"세탁이 끝났음에도 불구하고 건조한 환경에서 젖은 옷에서 나는 곰팡이 또는 시큼한 냄새는 세탁조 내부의 물때와 곰팡이가 원인일 가능성이 높다."},{"topic":"베이킹소다세탁","label":"세탁물에 하얀 가루가 남는 경우","detail":"세제 찌꺼기나 섬유 유연제 잔여물이 완전히 헹궈지지 않아 옷감에 하얗게 남아 피부 자극을 유발하는 현상이다."},{"topic":"과탄산소다","label":"세탁조 물때가 심할 때","detail":"세탁기 내부의 물이 뿌옇거나 곰팡이 냄새가 날 때, 과탄산소다를 이용한 통세척을 시도하는 것이 일반적이다."},{"topic":"과탄산소다","label":"운동복 세탁 후","detail":"땀이나 체취가 강한 운동복을 세탁할 때, 일반 세제만으로는 제거되지 않는 냄새가 남아있을 수 있다."},{"topic":"구연산세탁","label":"세탁기 내부 고무 패킹","detail":"세탁물을 꺼낸 후 고무 패킹 틈새에 검거나 끈적한 곰팡이와 세제 찌꺼기가 눈에 띄게 남아있는 경우."},{"topic":"구연산세탁","label":"세탁물에서 나는 쉰내","detail":"세탁을 마쳤음에도 불구하고 꿉꿉하고 시큼한 냄새가 지속적으로 날 경우, 세탁기 내부의 물때나 곰팡이가 원인일 수 있다."},{"topic":"중성세제","label":"아기 세탁 세제 코너","detail":"제품 포장이나 설명에 'pH 5.5~7.5'와 같이 중성 범위가 명시되어 판매되는 것을 볼 수 있다."},{"topic":"중성세제","label":"섬유 유연제 사용 후","detail":"세제 잔여물을 중화시키고 섬유를 부드럽게 코팅하는 역할을 하는 중화제(Neutralizer)의 개념을 간접적으로 접할 수 있다."},{"topic":"울샴푸","label":"세탁기 세제 투입구","detail":"세제 종류별(울, 일반, 아기옷 등)로 분리된 투입구가 사용자가 세제의 목적을 명확히 인지하고 있음을 보여준다."},{"topic":"울샴푸","label":"세탁 후 옷감의 부드러움","detail":"세제 잔여물이 남지 않고 섬유가 본래의 부드러운 촉감을 유지하는 것이 세탁의 성공적인 결과를 시각적으로 보여준다."},{"topic":"드럼통돌이차이","label":"세탁기 구매 매장","detail":"매장 직원들이 두 세탁기 앞에서 각각의 장단점(물 절약 vs 강력 세척)을 강조하며 비교 설명하는 장면이 흔하다."},{"topic":"드럼통돌이차이","label":"세탁 후 옷감의 느낌","detail":"드럼세탁기로 세탁한 옷은 부드럽고 가벼운 느낌을, 통돌이로 세탁한 옷은 묵직하고 뽀득한 느낌을 받는 경우가 있다."},{"topic":"세탁조클리너","label":"세탁기 고무 패킹의 검은 곰팡이","detail":"세탁조와 외부가 만나는 고무 패킹 틈새는 물이 고이기 쉬워 곰팡이가 가장 먼저, 그리고 가장 심하게 자리 잡는 곳이다."},{"topic":"세탁조클리너","label":"세탁물에서 나는 꿉꿉한 냄새","detail":"이 냄새는 세탁물 자체가 아니라, 세탁조 내부에 축적된 찌꺼기 속의 박테리아가 분해되면서 발생하는 휘발성 유기 화합물 때문이다."},{"topic":"건조기사용법","label":"건조기 사용 후 옷감의 질감","detail":"적절히 건조된 옷은 부드러우면서도 형태가 유지되지만, 과건조된 옷은 지나치게 뻣뻣하거나 수축된 느낌을 준다."},{"topic":"건조기사용법","label":"건조기 내부의 먼지 필터","detail":"사용할 때마다 필터에 쌓인 보푸라기나 먼지를 확인하고 청소하는 습관이 필수적이다."},{"topic":"건조기수축","label":"새 옷을 건조한 후","detail":"세탁 후 건조된 옷이 구매 당시의 사이즈보다 눈에 띄게 작아져서 입지 못하는 경험을 할 때."},{"topic":"건조기수축","label":"옷장 속의 계절 옷","detail":"오래된 옷이나 니트류가 시간이 지나면서 건조기 사용 여부와 관계없이 전반적으로 줄어든 느낌을 받을 때."},{"topic":"건조볼","label":"빨래 건조대 주변의 습한 공기","detail":"건조기 사용을 고민하는 가장 큰 계기는 빨래 건조대 주변에 곰팡이 냄새를 유발하는 높은 습도가 형성되는 것을 목격할 때이다."},{"topic":"건조볼","label":"건조기 작동 후의 옷감","detail":"건조기 사용 후에도 옷감이 미지근하거나 눅눅한 느낌이 남아있다면, 건조 코스 설정이 불충분하거나 습도 관리가 필요하다는 신호이다."},{"topic":"스팀다리미","label":"여행지 호텔의 의류 관리 코너","detail":"스팀다리미나 스팀 살균기가 비치되어 있는 것은, 여행객들이 간편하게 의류의 주름과 냄새를 관리하려는 수요가 높다는 것을 보여준다."},{"topic":"스팀다리미","label":"섬유 유연제 사용 후의 의류","detail":"섬유 유연제는 스팀이 분사된 후 섬유 표면에 잔여 코팅막을 형성하여, 스팀의 효과를 보완하고 부드러움을 극대화하는 역할을 한다."},{"topic":"제습제종류","label":"신발장 구석의 곰팡이","detail":"습도가 높은 장마철에 곰팡이가 생겼다면, 단순히 제습제를 놓는 것 외에 통풍 구조 개선이 필요하다."},{"topic":"제습제종류","label":"빨래 건조대 주변의 물기","detail":"빨래를 건조할 때 발생하는 수증기는 국소적인 고습 환경을 만들므로, 환기나 추가 제습이 필수적이다."},{"topic":"방충제","label":"창문 틈새의 곰팡이","detail":"방충망과 창틀 사이의 미세한 틈새로 습기와 곰팡이 포자가 침투하는 것을 통해, 물리적 차단이 완벽하지 않음을 보여준다."},{"topic":"방충제","label":"특정 계절의 해충 증가","detail":"계절 변화에 따라 해충의 종류와 활동성이 달라지므로, 방충 방법 역시 시기별로 맞춤 전략이 필요함을 보여준다."},{"topic":"니트개는법","label":"세탁기 탈수 코스","detail":"세탁기에서 '울 코스'나 '섬세 코스'를 선택하는 것은 니트의 섬유 손상을 최소화하기 위한 물리적 제어 장치이다."},{"topic":"니트개는법","label":"옷장 속 니트의 늘어짐","detail":"오랫동안 옷걸이에 걸어둔 니트가 어깨나 밑단 부분이 눈에 띄게 늘어나 있다면, 건조 과정에서 중력의 영향을 과도하게 받았다는 증거이다."},{"topic":"셔츠개는법","label":"여행용 압축팩","detail":"공간 절약에 초점을 맞춘 압축팩은 셔츠의 형태를 강제로 변형시키므로, 도착 후 반드시 형태 복원 과정이 필요하다."},{"topic":"셔츠개는법","label":"옷장 속 꿉꿉한 냄새","detail":"제습제나 신문지 등을 활용하여 옷장 내부의 습도를 관리하는 행위 자체가 냄새와 형태 유지의 중요성을 보여준다."},{"topic":"옷수납방법","label":"계절 옷의 비닐 포장","detail":"장기 보관 의류가 비닐이나 전용 상자에 담겨 있다는 것은, 해당 의류가 습기나 해충으로부터 보호받아야 할 필요성이 크다는 것을 보여준다."},{"topic":"옷수납방법","label":"서랍 칸막이의 활용","detail":"속옷이나 양말을 개별 칸막이에 나누어 보관하는 것은, 작은 물건이라도 종류별로 분리하여 시각적 혼란을 막으려는 노력의 결과이다."},{"topic":"옷수납방법","label":"옷장 내의 높이 측정","detail":"수납 가구 구매 전, 옷장의 내부 높이를 정확히 측정하는 행위는 공간의 제약을 가장 먼저 인식하고 해결하려는 실질적인 과정이다."},{"topic":"계절옷정리","label":"옷장 구석의 곰팡이 냄새","detail":"계절이 바뀌어 옷을 정리한 후, 통풍이 잘 안 되는 곳에 습기가 머물면서 발생하는 가장 흔한 신호이다."},{"topic":"계절옷정리","label":"계절 옷 전용 수납함","detail":"비슷한 계절의 옷만 모아두는 전용 수납 시스템은, 옷장 내부의 시각적 혼란을 줄여준다."},{"topic":"이불보관","label":"계절이 바뀔 때의 이불장","detail":"이불장 문을 열었을 때 퀴퀴하고 곰팡이 냄새가 나는 것은 습도 조절 실패의 가장 명확한 신호이다."},{"topic":"이불보관","label":"보관용 커버의 변색","detail":"커버가 햇빛에 노출되거나 습한 환경에 오래 두면, 이불 소재와 별개로 커버 자체가 누렇게 변색되거나 곰팡이가 생길 수 있다."},{"topic":"베개세탁","label":"베개 커버의 변색","detail":"오래된 베개 커버의 모서리나 접히는 부분에 누렇게 변색된 부분이 발견된다면, 이는 세탁만으로는 해결되지 않는 내부의 오염이 원인일 수 있다."},{"topic":"베개세탁","label":"베개에서 나는 꿉꿉한 냄새","detail":"세탁을 마쳤음에도 불구하고 쉰내나 곰팡이 냄새가 지속적으로 난다면, 이는 세탁 과정 중의 건조 부족이나 세균의 깊은 침투가 원인일 가능성이 높다."},{"topic":"커튼세탁","label":"세탁기 탈수 후 커튼의 늘어짐","detail":"세탁 후 커튼을 건조대에 널었을 때, 원래의 형태보다 아래로 처지거나 늘어진 부분이 발견된다."},{"topic":"커튼세탁","label":"커튼의 특정 부분만 색이 바랜 경우","detail":"햇빛에 많이 노출되거나, 커튼 봉에 닿는 부분 등 특정 부위만 다른 부분과 확연히 색상 차이를 보인다."},{"topic":"카펫청소","label":"반려동물용 카펫","detail":"특정 냄새 제거 기능이 강화된 세제나, 냄새 분자를 중화시키는 탈취제가 필수적으로 사용된다."},{"topic":"카펫청소","label":"오래된 카펫의 변색","detail":"햇빛이나 생활 오염물로 인해 카펫의 색상이 부분적으로 바래거나 얼룩이 고착된 것을 볼 수 있다."},{"topic":"카펫청소","label":"습기가 많은 장마철","detail":"카펫을 청소한 후 건조가 제대로 되지 않아 곰팡이 냄새가 나거나 카펫의 섬유가 눅눅해진 것을 체감할 수 있다."},{"topic":"소파청소","label":"소파의 특정 부위 냄새","detail":"특정 부위(예: 등받이 아래, 쿠션 틈)에서 나는 퀴퀴한 냄새는 단순히 먼지가 아니라 습기와 결합된 세균 번식의 신호이다."},{"topic":"소파청소","label":"청소 후의 먼지 재발","detail":"청소 직후에도 짧은 시간 내에 먼지가 다시 쌓이는 현상은 소파 섬유 자체가 먼지를 끌어당기는 정전기적 특성을 가지고 있음을 보여준다."},{"topic":"매트리스청소","label":"아침에 기침이 심한 사람","detail":"특히 계절 변화나 건조한 환경에서 아침에 기침이나 코막힘이 심하다면, 매트리스의 알레르겐 축적을 의심해 볼 수 있다."},{"topic":"매트리스청소","label":"매트리스의 특정 부위 냄새","detail":"특정 부위(예: 등 쪽, 발 쪽)에서 꿉꿉하거나 곰팡이 같은 냄새가 난다면, 그 부분이 습기에 취약하거나 통풍이 잘 안 되는 사각지대일 가능성이 높다."},{"topic":"진드기제거","label":"침구류의 잦은 세탁 필요성","detail":"알레르기 증상이 있는 사람이 매일 아침 침구류를 세탁하거나 햇볕에 말리는 습관을 들이는 것 자체가 진드기 노출을 줄이는 행동 지표이다."},{"topic":"진드기제거","label":"습도가 높은 날의 곰팡이 증가","detail":"곰팡이와 진드기는 높은 습도라는 공통 분모를 가지며, 이 둘을 동시에 관리해야 근본적인 실내 환경 개선이 가능하다."},{"topic":"집먼지진드기","label":"아침에 일어났을 때의 코막힘","detail":"특히 건조하고 습도가 급변하는 아침 시간대에 코와 목의 불편함이 느껴진다면 진드기 배설물에 대한 노출이 원인일 수 있다."},{"topic":"집먼지진드기","label":"청소 후에도 지속되는 피부 가려움","detail":"표면적인 청소만으로는 제거되지 않는 미세한 진드기 알레르겐이 피부에 남아 만성적인 가려움을 유발할 수 있다."},{"topic":"수능구조","label":"학원가 간판의 과목 집중 현상","detail":"특정 과목이나 특정 유형의 문제 풀이법을 강조하는 학원들이 많은 것은, 수능이 특정 영역의 지식 습득을 가장 효율적이고 확실하게 점수화하는 방법으로 인식되기 때문이다."},{"topic":"수능구조","label":"학생들의 시간표 구성","detail":"수능을 대비하는 학생들은 학교 수업 시간 외에 특정 과목의 심화 학습에 압도적으로 많은 시간을 할애하는 경향을 보인다."},{"topic":"수능과목","label":"학원가 상담 분위기","detail":"입시 학원가에서는 여전히 '내신 관리'와 '수능 점수'를 분리하여, 두 마리 토끼를 잡아야 한다는 압박감을 조성한다."},{"topic":"수능과목","label":"학생부 기록지","detail":"생기부에 기록된 세부 활동 내용이 단순히 활동 목록 나열에 그치지 않고, 학업적 질문과 연결되는 과정이 중요하게 부각된다."},{"topic":"국어선택과목","label":"학교 진로 상담 시간","detail":"학생들이 단순히 인기 과목이나 높은 등급을 받은 과목을 선택하기보다, 자신의 흥미와 적성을 연결한 과목 조합을 고민하는 모습이 관찰된다."},{"topic":"국어선택과목","label":"대학 모집 요강 분석","detail":"대학들이 과거의 과목명 대신 '학문 영역'이나 '역량'을 기준으로 반영 과목을 재설명하는 경향이 나타난다."},{"topic":"수학선택과목","label":"학교 진로 상담 시간","detail":"학생들이 단순히 인기 과목이나 높은 등급을 받은 과목을 선택하기보다, 자신의 희망 전공과 연관된 과목을 찾아 상담하는 모습이 늘고 있다."},{"topic":"수학선택과목","label":"학생부 기록의 세특(세부 능력 및 특기 사항)","detail":"과목 성적 자체보다, 해당 과목에서 어떤 주제를 깊이 있게 탐구하고 어떤 방식으로 지식을 확장했는지가 구체적으로 기록되는 추세가 뚜렷하다."},{"topic":"탐구과목선택","label":"고등학교 학과 안내 책자","detail":"과목별로 '진로 연계'라는 문구가 붙어 있어, 선택이 곧 진로의 결정처럼 느껴지게 만든다."},{"topic":"탐구과목선택","label":"선배들의 합격 스토리","detail":"특정 과목 조합을 선택한 선배의 성공 사례가 마치 '정답 공식'처럼 인식되어 과도한 불안감을 조성한다."},{"topic":"절대평가상대평가","label":"학교 성적표","detail":"과목별로 'A-'와 같은 성취도와 함께, 학년 전체의 '1등급' 등의 석차 정보가 동시에 기재되어 평가의 이중성을 보여준다."},{"topic":"절대평가상대평가","label":"학습 멘토링 상담","detail":"학생이 '성적'이라는 숫자에 좌절할 때, 멘토가 '성장 과정'이나 '노력'에 초점을 맞추어 평가의 관점을 전환시키려 한다."},{"topic":"수능등급컷","label":"학원가 입시 컨설팅","detail":"수능 등급컷의 과거 데이터를 분석하고 이를 미래 합격 예측에 활용하는 컨설팅 자료가 끊임없이 생성된다."},{"topic":"수능등급컷","label":"수능 직후의 입시 커뮤니티","detail":"실시간으로 발표되는 과목별 평균 점수와 등급컷을 두고 수험생들 사이에서 불안감과 기대감이 교차하는 모습을 보인다."},{"topic":"표준점수백분위","label":"대학 입시 전형 안내문","detail":"전형 요소별로 표준점수 또는 백분위 점수 사용 여부를 명시하며, 점수 산출 방식에 대한 설명을 제공한다."},{"topic":"표준점수백분위","label":"학습지 또는 모의고사 분석 자료","detail":"과거 시험의 점수 분포를 그래프로 보여주며, 평균과 표준편차를 계산하여 난이도를 분석하는 형태로 제시된다."},{"topic":"최저학력기준","label":"대학 모집요강 발표","detail":"매년 입시 시즌이 되면, 대학들이 전년도 입시 결과와 사회적 요구를 반영하여 최저학력기준의 과목이나 등급을 미세하게 조정하는 움직임이 포착된다."},{"topic":"최저학력기준","label":"학부모 간의 대화","detail":"자녀의 입시 준비 과정에서 '최저학력기준 충족' 여부가 학업 성적 자체보다 더 큰 스트레스 요인이나 목표로 인식되는 경우가 많다."},{"topic":"수시정시차이","label":"학교 생활기록부(생기부)의 변화","detail":"단순한 과목 점수 기록을 넘어, 학생의 세부 활동 내용(탐구 보고서, 발표 내용)을 구체적으로 서술하는 경향이 강화되고 있다."},{"topic":"수시정시차이","label":"학원가 및 컨설팅 시장의 과열","detail":"수시/정시 전형의 복잡성과 불확실성 때문에, 입시 전략을 짜주는 사교육 시장이 매우 거대하고 전문화되어 있다."},{"topic":"수시전형종류","label":"학교생활기록부(생기부) 첨삭 서비스","detail":"학생들이 자신의 활동 내용이나 세특 기재 방향에 대해 전문가의 조언을 구하는 것은, 정성적 평가 요소의 중요성이 커졌음을 보여준다."},{"topic":"수시전형종류","label":"대학별 전형 가이드북의 복잡성","detail":"매년 대학들이 전형 요소의 반영 비율이나 반영 과목을 미묘하게 변경하는 것은, 입시 제도가 매우 유동적이고 복잡한 구조를 가지고 있음을 시사한다."},{"topic":"학생부교과","label":"학교 발표 자료","detail":"학생들에게 '성적 관리'와 '세특 기록'을 병행하라는 조언이 끊임없이 나오는 것은, 두 요소가 분리된 것이 아니라 상호 보완적임을 보여준다."},{"topic":"학생부교과","label":"학생들의 학습 계획표","detail":"단순히 시험 대비 과목 외에, '탐구 보고서 작성'이나 '심화 독서' 시간이 별도로 배정되는 것은, 점수 외의 역량 확보가 중요해졌음을 의미한다."},{"topic":"학생부종합","label":"학교 발표회/탐구 보고서","detail":"학생들이 단순히 지식을 암기하는 것을 넘어, 스스로 질문을 던지고 해결책을 제시하는 과정이 기록으로 남는다."},{"topic":"학생부종합","label":"교과 수업 중 토론 참여 모습","detail":"수업 시간에 적극적으로 의견을 제시하거나, 다른 학생의 논리를 비판적으로 수용하는 모습이 세특에 반영된다."},{"topic":"논술전형","label":"논술 첨삭 서비스의 증가","detail":"시중에 논술 첨삭 서비스가 폭발적으로 증가하는 것은, 논술이라는 평가 방식 자체가 '정답'이 아닌 '최적의 논리 구조'를 찾아내는 과정이기 때문이다."},{"topic":"논술전형","label":"학회나 세미나 발표 경험의 중요성 부각","detail":"단순히 지식을 암기하는 것보다, 자신이 배운 내용을 다른 사람 앞에서 논리적으로 설명하고 질문에 답하는 경험이 논술 실력 향상에 직접적인 도움을 준다는 인식이 확산되고 있다."},{"topic":"특기자전형","label":"학교 포트폴리오 전시회","detail":"학생들이 자신의 특기 관련 탐구 보고서나 결과물을 전시할 때, 단순한 결과물 나열보다 '탐구 과정의 어려움과 해결 방법'을 설명하는 발표가 더 높은 평가를 받는 경향이 있다."},{"topic":"특기자전형","label":"학과별 특강 및 세미나","detail":"특기자전형을 준비하는 학생들이 지원 학과 관련 세미나에 참여하여 질문을 던지거나 발표하는 모습은, 그 특기가 학문적 호기심에서 비롯되었음을 보여주는 강력한 증거가 된다."},{"topic":"정시가나다군","label":"학원가/인강 플랫폼의 과목별 광고","detail":"특정 과목의 점수 향상에 대한 광고가 집중되는 것은, 해당 과목이 입시에서 높은 반영 비율을 차지하거나 최저학력기준으로 지정되었기 때문이다."},{"topic":"정시가나다군","label":"학부모 간의 대화","detail":"자녀의 전공 적합성이나 내신 성적을 언급하며 '정시도 괜찮다'는 이야기를 하는 것은, 정시가 단순히 점수만으로 평가되는 전형이 아님을 인지하고 있기 때문이다."},{"topic":"교차지원","label":"모둠 프로젝트 발표","detail":"한 학생이 자료 조사에 강점을 보이고, 다른 학생이 발표 구성에 강점을 보이는 등, 각자의 강점을 조합하여 결과물을 완성하는 과정에서 교차지원의 원리가 작동한다."},{"topic":"교차지원","label":"멘토-멘티 활동","detail":"학업적 지식뿐만 아니라, 진로 탐색이나 학습 습관 등 비학업적 영역에서 선배나 또래가 후배에게 실질적인 조언을 제공하는 모습에서 나타난다."},{"topic":"내신등급계산","label":"학교별 내신 등급 분포 그래프","detail":"같은 2등급이라도 학교마다 학생들의 분포가 달라, 같은 등급이라도 실질적인 학업 수준의 차이가 크게 나타나는 것을 확인할 수 있다."},{"topic":"내신등급계산","label":"학생부 기록지(세특)","detail":"단순히 'A+'라는 점수 대신, 'OO 탐구 활동을 통해 ~한 방식으로 깊이 있게 사고함'과 같은 서술형 기록이 학업 역량을 보여주는 핵심 증거가 된다."},{"topic":"내신산출","label":"학교 성적표","detail":"단순한 점수와 등급 외에, 세부 능력 및 특기 사항(세특)에 기록된 구체적인 활동 내용이 학생의 역량을 보여주는 주요 지표가 된다."},{"topic":"내신산출","label":"학원/컨설팅 상담","detail":"학생들이 내신 성적을 분석할 때, 단순히 등급을 올리는 것보다 '어떤 과목의 어떤 영역'을 보완해야 할지 구체적인 진단에 초점을 맞춘다."},{"topic":"고교학점제","label":"학교 학사 일정표","detail":"기존의 학년별/반별 고정된 시간표 대신, 학생들이 자신의 진로에 맞춰 다양한 과목을 조합하여 수강하는 형태로 변화하는 것이 관찰된다."},{"topic":"고교학점제","label":"학생의 포트폴리오","detail":"단순한 성적표 대신, 학생이 어떤 과목을 왜 선택했고, 그 과정에서 어떤 결과물(보고서, 프로젝트)을 만들어냈는지 기록된 포트폴리오가 중요해지고 있다."},{"topic":"선택과목이수","label":"학교 진로 상담 시간","detail":"학생들이 특정 전공 분야에 대한 정보를 얻기 위해, 해당 전공과 관련된 선택과목 목록을 집중적으로 검색하고 상담을 요청하는 모습에서 그 중요성을 알 수 있다."},{"topic":"선택과목이수","label":"생기부 세특(세부 능력 특기 사항) 작성","detail":"교사가 학생의 선택과목 수행평가 결과와 탐구 보고서를 연결하여, 학생의 학문적 성장 과정을 서술하는 데 많은 공을 들인다."},{"topic":"세특","label":"학교 발표 자료","detail":"학생들이 교과 지식을 바탕으로 직접 설계한 실험 과정이나, 기존 이론에 의문을 제기하는 질문들이 세특의 좋은 소재가 된다."},{"topic":"세특","label":"학생의 자기소개서 초안","detail":"학생들이 자신의 학업 경험을 정리하며, 어떤 활동을 '무엇을 배웠다'는 관점보다 '어떤 질문을 던졌다'는 관점으로 재구성하는 과정을 거친다."},{"topic":"생기부관리","label":"탐구 보고서 제출","detail":"학교에서 특정 주제에 대해 심화 보고서를 작성하게 하는 활동은, 학생이 스스로 지적 질문을 던지고 해결책을 찾아가는 과정을 생기부에 기록할 기회를 제공한다."},{"topic":"생기부관리","label":"교과 수업 중 발표 자료","detail":"단순히 발표 자료를 제출하는 것을 넘어, 그 자료를 만들기 위해 어떤 자료를 참고했고 어떤 논리적 비판을 거쳤는지 과정이 중요하게 인식되기 시작했다."},{"topic":"독서활동","label":"토론 모임의 주제 선정","detail":"최근 읽은 책의 특정 개념을 가져와서, 현실 사회 문제와 연결하여 찬반 토론의 핵심 논거로 사용하는 경우."},{"topic":"독서활동","label":"업무 보고서의 배경 지식","detail":"업무와 직접 관련 없는 분야의 책에서 얻은 통찰(예: 생물학적 원리)을 가져와서, 비즈니스 모델의 새로운 관점으로 제시하는 경우."},{"topic":"동아리활동입시","label":"학생부 기록의 '탐구 과정' 서술","detail":"단순히 'A를 했다'가 아니라, 'A를 하다가 B라는 문제에 부딪혀 C라는 방법을 적용해 해결했다'는 서술 방식이 중요하게 다뤄진다."},{"topic":"동아리활동입시","label":"교과 세특의 '연계성' 언급","detail":"동아리 활동에서 배운 개념을 특정 과목의 수업 내용과 연결하여 발표하거나 보고서로 제출하는 경우, 높은 평가를 받는다."},{"topic":"봉사활동입시","label":"학교 동아리 발표회 주제","detail":"최근 동아리 발표 주제가 단순 취미 공유에서 벗어나, '지역 사회의 환경 문제 해결 방안' 등 사회적 이슈와 연결되는 경향을 보인다."},{"topic":"봉사활동입시","label":"학생의 포트폴리오 구성","detail":"단순히 활동 사진을 나열하는 대신, 활동을 통해 얻은 '배움의 과정'과 '개선점'을 서술하는 보고서 형태가 주류가 되고 있다."},{"topic":"자율활동","label":"학교 발표회/학술제 보고서","detail":"단순한 결과물 제시를 넘어, '왜 이 주제를 선택했는지'에 대한 질문과 '이 주제를 통해 어떤 학문적 한계에 부딪혔는지'에 대한 성찰이 포함되어야 한다."},{"topic":"자율활동","label":"학생의 자기소개서 초안","detail":"활동의 나열식 서술 대신, 활동을 통해 변화한 '사고의 방식'이나 '관점의 전환'을 서술하는 것이 핵심이다."},{"topic":"진로활동","label":"학교 수행평가 보고서","detail":"단순히 자료를 요약하는 보고서가 아니라, 특정 문제의 원인을 분석하고 자신만의 해결책을 제시하는 '문제 해결 과정'이 포함되어야 의미가 있다."},{"topic":"진로활동","label":"대학 면접에서의 질문","detail":"지원자가 특정 전공 분야에 대해 '왜' 이 학문을 공부하고 싶은지, 그 이유를 자신의 경험과 연결하여 논리적으로 설명할 수 있어야 한다."},{"topic":"교내상","label":"학교 수행평가 보고서","detail":"단순히 결과물 제출에 그치지 않고, 탐구 과정에서 겪은 어려움과 이를 해결하기 위해 본인이 취한 논리적 사고 과정을 서술하는 것이 중요하다."},{"topic":"교내상","label":"진로 탐색 프로그램 안내문","detail":"학교가 제공하는 다양한 프로그램 목록을 볼 때, 단순히 참여하는 것보다 어떤 프로그램이 나의 어떤 역량과 연결되는지 분석하는 시각이 필요하다."},{"topic":"자기소개서폐지","label":"대학의 전형 안내문","detail":"매년 전형 요소가 '학생부 100%' 또는 '면접 70% + 서류 30%' 등으로 세분화되어 제시되며, 자기소개서 항목이 아예 없는 경우가 늘어난다."},{"topic":"자기소개서폐지","label":"학생들의 입시 상담 내용","detail":"자기소개서 작성법보다는 '생기부의 어떤 활동을 어떻게 심화시켜야 하는가'에 대한 조언이 주를 이루는 경향이 뚜렷해진다."},{"topic":"면접형태","label":"꼬리 질문의 연속","detail":"지원자가 제시한 답변의 특정 부분(예: '이 프로젝트의 성공 요인')을 집요하게 파고드는 질문이 이어질 때, 답변의 깊이와 논리적 빈틈이 드러난다."},{"topic":"면접형태","label":"비언어적 신호 관찰","detail":"답변 내용뿐만 아니라, 면접 중 눈빛의 흔들림, 자세의 변화, 목소리의 톤 변화 등 비언어적 신호가 지원자의 자신감과 진정성을 판단하는 중요한 근거가 된다."},{"topic":"제시문면접","label":"학술 세미나 발표","detail":"참가자들이 기존 연구의 한계점(제시문)을 분석하고, 이를 극복할 수 있는 새로운 가설이나 방법론을 제안하는 방식으로 진행된다."},{"topic":"제시문면접","label":"논문 리뷰 과정","detail":"심사위원이 논문의 핵심 논리 구조와 전제에 대해 날카로운 질문을 던지며, 저자에게 논리의 허점을 찾아내도록 요구한다."},{"topic":"서류평가","label":"자기소개서의 방향성","detail":"서류평가 요소가 늘어남에 따라, 학생들은 자신의 모든 활동을 하나의 일관된 '스토리'로 엮어내려 노력하는 경향을 보인다."},{"topic":"서류평가","label":"대학별 면접 질문의 변화","detail":"서류에 기록된 특정 탐구 주제나 활동에 대해 심층적인 질문을 던지는 경향이 강해지면서, 기록의 깊이가 중요해진다."},{"topic":"블라인드평가","label":"기업 채용 공고의 문구","detail":"‘블라인드 채용’이라는 문구가 붙는 것만으로도 지원자들은 평가가 공정할 것이라는 심리적 기대와 신뢰를 갖게 된다."},{"topic":"블라인드평가","label":"면접관의 질문 방식","detail":"면접관이 지원자의 개인사 질문을 자제하고, 오직 '과제 수행 과정'이나 '직무 관련 경험'에만 집중하는 경향이 강화된다."},{"topic":"고른기회전형","label":"학교 생활기록부의 서술형 평가","detail":"단순히 성적이 좋은 학생보다, 특정 주제에 대해 깊이 있는 질문을 던지고 탐구 보고서를 작성한 기록이 더 주목받는 경향이 있다."},{"topic":"고른기회전형","label":"학부모들의 입시 상담 내용","detail":"성적 우수자 전형과 함께, '우리 아이가 가진 배경적 어려움을 어떻게 보완하여 입시에서 성공할 수 있을까'에 대한 고민이 깊어지고 있다."},{"topic":"지역균형선발","label":"지역 대학의 학과 신설/폐지 공지","detail":"지역 인재 유입을 위해 특정 학과를 신설하거나, 혹은 경쟁력 부족으로 학과를 폐지하는 결정은 지역 균형 발전의 압박을 보여준다."},{"topic":"지역균형선발","label":"지역 대학의 취업률 홍보 자료","detail":"지역 인재들이 지역 대학 졸업 후 지역 기업에 취업한다는 통계 자료는 제도의 성공적인 작동 사례로 홍보된다."},{"topic":"농어촌전형","label":"지역 대학의 취업률 공시","detail":"지역 대학의 취업률이 낮은 것은 단순히 학생들의 역량 문제라기보다, 지역 내 산업 구조가 학생들의 전공과 연결되지 못했기 때문이다."},{"topic":"농어촌전형","label":"지역 특화 산업 육성 계획","detail":"지자체가 특정 산업(예: 바이오, 관광)을 지정하고 인재 양성 과정을 설계하는 것이, 전형 제도보다 더 강력한 인재 유입 동기가 될 수 있다."},{"topic":"재수반수","label":"학원가 주변의 분위기","detail":"재수 학원가나 독서실 주변은 특유의 긴장감과 경쟁적인 분위기가 감돌며, 이는 재수생들의 심리적 압박을 시각적으로 보여준다."},{"topic":"재수반수","label":"학습 계획표의 변화","detail":"재수/반수를 결심한 학생들은 이전보다 훨씬 세분화되고 강도 높은 시간표를 작성하며, 이는 시간 관리에 대한 강박을 보여준다."},{"topic":"반수타이밍","label":"학원가 포스터","detail":"‘반수 성공’, ‘N수 합격’ 등의 문구는 특정 시기에 불안감을 느끼는 학부모와 학생들의 심리를 자극하는 상업적 신호로 작용한다."},{"topic":"반수타이밍","label":"수능 성적표","detail":"목표 대학의 합격선과 자신의 성적표를 비교하는 순간, '아직 부족하다'는 객관적인 격차 인식이 반수 결심의 가장 큰 계기가 된다."},{"topic":"편입학","label":"스터디 카페의 전공 서적과 어학 교재 혼재","detail":"편입을 준비하는 학생들이 전공 지식과 외국어 능력이라는 두 가지 영역을 동시에, 그리고 병행하여 학습하고 있음을 보여준다."},{"topic":"편입학","label":"학점은행제 수료증","detail":"정규 대학 과정을 거치지 않고도 학점을 취득하여 학업의 연속성을 확보하려는 노력이 사회적으로 일반화되었음을 보여준다."},{"topic":"편입영어","label":"스터디 카페의 영어 교재","detail":"최신 트렌드를 반영하여 단순히 문법서 대신, 학술지나 논문 발췌문 기반의 독해 자료가 주력으로 사용되는 경향을 보인다."},{"topic":"편입영어","label":"학원 상담 시의 질문","detail":"학생들이 '어휘'와 '문법' 중 어느 것부터 시작해야 하는지 고민하는 모습에서, 학습의 우선순위에 대한 혼란이 여전히 존재함을 알 수 있다."},{"topic":"학사편입일반편입","label":"대학 커뮤니티의 정보 혼란","detail":"편입학 관련 커뮤니티에서 일반편입과 학사편입의 자격 요건 및 준비 방법이 뒤섞여 있어 정확한 정보 구분이 어렵다."},{"topic":"학사편입일반편입","label":"학점은행제 상담 과정","detail":"개인이 자신의 학점 이수 계획을 세울 때, 어떤 학점을 어떤 전공 분야로 설계해야 편입 목표 대학에 유리한지 컨설팅이 필요한 상황이 자주 발생한다."},{"topic":"전과제도","label":"면접관의 질문","detail":"지원자가 전과기록에 대해 질문을 받았을 때, 단순히 숨기거나 변명하는 것이 아니라, 그 경험을 통해 무엇을 배웠다고 설명하는 능력이 중요해진다."},{"topic":"전과제도","label":"지역 사회의 시선","detail":"출소자가 지역 사회에 돌아왔을 때, 주변 이웃들의 무관심이나 편견 어린 시선 자체가 재범의 위험 요인으로 작용할 수 있다."},{"topic":"복수전공부전공","label":"자기소개서의 '성장 과정' 항목","detail":"단순히 '무엇을 공부했다'를 나열하는 대신, 'A라는 지식을 B라는 상황에 적용하여 C라는 결과를 얻었다'는 구조로 서술하는 것이 핵심이다."},{"topic":"복수전공부전공","label":"다양한 분야의 협업 프로젝트","detail":"공학 전공자가 마케팅 전공자와 함께 기획한 프로젝트처럼, 이질적인 배경지식을 가진 사람들이 모여 시너지를 내는 사례가 증가하고 있다."},{"topic":"계절학기","label":"방학 중 수강 신청 폭주","detail":"방학 기간에 특정 인기 과목의 수강 신청이 정원 초과로 마감되는 현상은 계절학기의 높은 수요를 보여준다."},{"topic":"계절학기","label":"학사 일정표의 '계절학기' 표시","detail":"매년 학사 일정표에 계절학기 개설 여부와 기간이 명시되는 것은 이것이 정규 학기만큼 중요한 학사 요소로 인식됨을 보여준다."},{"topic":"학점포기","label":"학점 관리 상담","detail":"학기 초나 학기 중 성적표를 확인하며 '이번 과목은 포기할까?'라는 고민을 하는 학생들의 상담 기록에서 흔히 발견된다."},{"topic":"학점포기","label":"성적표의 평점 계산 방식","detail":"성적표 하단에 '성적 반영 과목' 또는 '성적 제외 과목' 등의 명시적인 구분이 되어 있어, 어떤 과목이 포기 대상인지 직관적으로 알 수 있다."},{"topic":"성적장학금","label":"학기 초 성적표 확인","detail":"성적표의 평점(GPA)을 확인하는 순간, 다음 학기 장학금 수혜 가능성이라는 압박감과 목표 의식이 동시에 느껴진다."},{"topic":"성적장학금","label":"학점 관리 관련 커뮤니티","detail":"성적을 올리기 위한 스터디 그룹이나 학점 관리를 위한 시간표 짜기 등, 학업 성취를 최우선 과제로 삼는 모습이 관찰된다."},{"topic":"국가장학금소득분위","label":"장학금 신청 안내문","detail":"신청서에 '소득분위 확인서'를 제출하도록 요구하며, 이는 가구의 경제적 상태가 공식적으로 심사되고 있음을 보여준다."},{"topic":"국가장학금소득분위","label":"가족 구성원의 이사 또는 직장 변동","detail":"가족 중 누군가가 이사를 가거나 직장을 옮기면, 소득 및 재산 변동으로 인해 소득분위 재산정이 필요하다는 안내를 받게 된다."},{"topic":"학자금대출종류","label":"졸업 후 첫 급여 명세서","detail":"월급에서 학자금대출 원리금 상환액이 고정적으로 공제되는 것을 보며, 학업이 끝난 후에도 경제적 의무가 지속됨을 체감한다."},{"topic":"학자금대출종류","label":"학자금대출 상담 창구","detail":"상환 방식 변경, 이자율 조정, 상환 유예 등 복잡한 금융 용어와 조건들을 안내받으며 제도의 복잡성을 인지한다."},{"topic":"취업후상환","label":"사회 초년생의 재정 계획 상담","detail":"첫 월급을 받자마자 가장 먼저 학자금 대출의 상환 스케줄과 소득 기준을 확인하는 과정에서 이 제도의 존재가 체감된다."},{"topic":"취업후상환","label":"직장 이직 및 이직 준비 기간","detail":"소득이 일시적으로 끊기거나 줄어드는 기간에 상환 유예나 조정 가능 여부를 문의하는 것이 현실적인 재정 계획의 핵심이 된다."},{"topic":"근로장학","label":"학과 사무실의 공지사항","detail":"학기 초에 근로장학 신청 기간과 자격 요건이 공지되며, 이는 학생들의 학업 계획과 경제적 계획을 동시에 점검하게 만든다."},{"topic":"근로장학","label":"직무 관련 포트폴리오","detail":"학생이 제출하는 포트폴리오에 '근로장학 기간 동안 수행한 프로젝트'가 포함되어 있다면, 이는 단순한 아르바이트 이상의 전문성을 증명한다."},{"topic":"교환학생","label":"국제 교류 프로그램 모집 공고","detail":"요구되는 어학 성적과 학점 평균 등의 기준이 명확하게 제시되어, 준비해야 할 구체적인 목표치를 보여준다."},{"topic":"교환학생","label":"해외 대학의 온라인 강의 수강","detail":"실제 현지 학업 환경을 간접적으로 경험하며, 문화적 차이와 학문적 접근 방식을 미리 체감할 수 있다."},{"topic":"어학연수휴학","label":"이력서의 '경력/활동' 항목","detail":"공백기 활동을 나열할 때, 단순히 활동명만 적는 것이 아니라 '기간 동안 어떤 문제에 직면했고, 어떤 방법으로 해결했는지'를 서술하는 것이 중요하다."},{"topic":"어학연수휴학","label":"면접관의 질문 패턴","detail":"면접에서 공백기에 대한 질문은 '왜 쉬었는가?'가 아니라 '그 기간 동안 무엇을 준비했고, 그것이 우리 회사/전공에 어떻게 기여할 것인가?'로 심화되는 경향이 있다."},{"topic":"자퇴재입학","label":"학사 상담센터의 재입학 전용 프로그램","detail":"학교에서 자퇴생을 대상으로 재입학 전 학업 역량 진단 및 심리 상담을 제공하는 프로그램이 운영된다."},{"topic":"자퇴재입학","label":"학점은행제 활용 계획서","detail":"대학 재입학을 준비하는 학생이 부족한 학점을 외부 교육기관을 통해 미리 이수하며 학업 공백을 메우는 사례가 보인다."},{"topic":"검정고시","label":"성인 학습자의 재도전","detail":"취업이나 직무 전환을 위해 일정 수준의 학력이 필요해지면서, 학업을 중단했던 성인들이 검정고시를 준비하는 모습에서 그 수요를 확인할 수 있다."},{"topic":"검정고시","label":"학원가 및 온라인 강의 시장","detail":"검정고시 대비 전문 학원이나 온라인 강의가 활발하게 운영되는 것은, 제도권 교육 외의 경로로 학력 취득을 원하는 수요가 크다는 방증이다."},{"topic":"학력인정","label":"직무 역량 중심의 채용 공고","detail":"학력이나 전공명 대신 '데이터 분석 능력', '프로젝트 관리 경험' 등 구체적인 역량 키워드를 요구하는 채용 공고가 늘어나는 현상."},{"topic":"학력인정","label":"온라인 자격증의 증가","detail":"대학 학위 외에도 특정 기술이나 지식을 증명하는 온라인 플랫폼 기반의 자격증이나 수료증이 학력의 보조적 역할을 수행하는 모습."},{"topic":"방통고","label":"직장 내 교육 프로그램 홍보","detail":"기업들이 직원들에게 외부 학위 취득이나 자격증 취득을 장려하는 것은, 인재의 역량 강화가 곧 기업의 경쟁력으로 직결된다는 인식이 반영된 것이다."},{"topic":"방통고","label":"퇴근 후 온라인 강의 수강 화면","detail":"직장인들이 저녁 시간을 활용해 학습하는 모습은, 학업이 더 이상 '청년기의 일시적 목표'가 아니라 '평생의 지속적인 투자'임을 보여준다."},{"topic":"대안학교학력","label":"대학 자기소개서/면접","detail":"학교 이름보다는 '어떤 경험을 통해 어떤 문제를 해결했는지'에 대한 구체적인 과정과 깊이를 묻는 질문이 늘어나고 있다."},{"topic":"대안학교학력","label":"온라인 학습 플랫폼의 성장","detail":"특정 학교의 물리적 공간을 벗어나, 관심 분야의 전문가에게 직접 지식을 습득하고 인증받는 과정이 일반화되고 있다."},{"topic":"홈스쿨링제도","label":"방과 후 활동의 다양성","detail":"학교 외의 다양한 사설 학원, 동아리, 문화센터 활동에 참여하는 모습은 홈스쿨링이 대체하려는 사회적 경험의 필요성을 보여준다."},{"topic":"홈스쿨링제도","label":"학부모의 교육 관련 커뮤니티","detail":"온라인이나 오프라인에서 홈스쿨링 정보를 공유하고 커리큘럼을 논의하는 활동은, 교육의 주체가 학교에서 가정으로 이동했음을 보여준다."},{"topic":"의대정원","label":"지역 병원의 공고 모집 공고","detail":"특정 지역이나 필수과목(소아과, 산부인과 등)의 의사 자리가 지속적으로 공석으로 남아있는 현상을 통해 인력 불균형을 체감할 수 있다."},{"topic":"의대정원","label":"의료 정책 관련 언론 보도","detail":"정부와 의료계 간의 정원 및 수가 책정 관련 논쟁이 주기적으로 발생하며, 이는 정책의 불확실성을 보여준다."},{"topic":"약대입시","label":"학교 과학 탐구 보고서","detail":"단순히 지식을 나열하는 보고서보다, 실험 과정에서 발생한 오류를 분석하고 개선점을 제시하는 비판적 사고 과정이 강조된다."},{"topic":"약대입시","label":"의료 관련 봉사활동 경험","detail":"단순한 시간 채우기가 아니라, 환자나 의료진과의 상호작용 속에서 공감 능력이나 문제 해결 능력을 발휘한 경험이 중요하게 작용한다."},{"topic":"교대사대","label":"직무 관련 자격증 취득","detail":"학업 외적으로 특정 분야의 전문성을 증명하는 자격증 취득에 많은 시간과 비용을 투자하는 모습에서 간접적인 학력 보완 욕구를 볼 수 있다."},{"topic":"교대사대","label":"온라인 강의 수강 기록","detail":"퇴근 후나 주말을 이용해 온라인 교육 플랫폼에서 다양한 강좌를 듣는 행위 자체가 자기계발의 필요성을 보여준다."},{"topic":"로스쿨입시","label":"법률 관련 뉴스 기사","detail":"최근 사회적 이슈(예: 챗GPT 관련 법적 책임, 환경 규제)를 다루는 기사에서, 법률 전문가들이 단순히 법 조항을 언급하는 것을 넘어 사회적 맥락과 윤리적 관점을 함께 논하는 경향이 뚜렷하다."},{"topic":"로스쿨입시","label":"학부 졸업 작품 또는 공모전","detail":"단순히 학점을 잘 받는 것보다, 전공 지식을 활용하여 실제 사회 문제를 정의하고 해결책을 제시하는 프로젝트 경험이 자기소개서에서 높은 평가를 받는다."},{"topic":"의치한수","label":"치과 상담실의 포스터","detail":"임플란트, 브릿지, 틀니 등 다양한 보철물 옵션이 나열되어 있어, 환자에게 선택의 폭과 복잡성을 동시에 제시한다."},{"topic":"의치한수","label":"식사 후의 발음 변화","detail":"치아 상실 부위의 보철물 상태나 교합 문제가 제대로 해결되지 않으면, 발음이 부정확해지는 현상이 나타난다."},{"topic":"계좌이체한도","label":"대규모 결제 직전 알림창","detail":"이체 금액이 한도를 초과할 경우, '한도 초과로 거래가 제한되었습니다'라는 문구와 함께 증액 방법을 안내받는다."},{"topic":"계좌이체한도","label":"새로운 기기에서의 로그인 시","detail":"평소 사용하지 않던 스마트폰이나 PC에서 접속하면, 추가 인증(OTP, SMS 등)을 요구하며 일시적인 거래 제한이 걸린다."},{"topic":"이체한도상향","label":"고액 이체 시 문자 알림","detail":"평소와 다른 고액 이체 시도에 대해 금융기관에서 추가 인증이나 확인 절차를 거치라는 문자가 오는 것이 대표적인 예시이다."},{"topic":"이체한도상향","label":"은행 창구 방문 요청","detail":"온라인 시스템에서 처리할 수 없는 매우 큰 금액의 이체는 결국 고객이 직접 은행 창구를 방문하여 담당자와 상담해야 한다."},{"topic":"1일이체한도","label":"ATM 기기 화면","detail":"이체 한도가 초과되거나 제한될 경우, '이체 한도 초과' 또는 '거래가 제한되었습니다'와 같은 명확한 오류 메시지를 받게 된다."},{"topic":"1일이체한도","label":"은행 앱 알림 메시지","detail":"주요 금융 정책 변경이나 보안 강화 시, 이체 한도 변경에 대한 공지 알림을 통해 고객에게 사전 고지한다."},{"topic":"OTP발급","label":"로그인 시 팝업되는 6자리 숫자","detail":"은행 사이트나 서비스 접속 시, 비밀번호 입력 직후 별도로 코드를 입력하라는 창이 뜨는 것이 바로 OTP를 이용하는 순간이다."},{"topic":"OTP발급","label":"스마트폰 앱 알림","detail":"특정 금융 거래가 발생할 때, 앱을 통해 '인증번호를 입력하세요'라는 알림을 받는 경우, 이는 OTP를 활용한 추가 검증 과정이다."},{"topic":"보안카드","label":"ATM 기기","detail":"카드와 비밀번호 입력 후, 추가적으로 보안카드 번호를 입력해야만 거래가 완료되는 과정을 통해 그 필요성을 체감한다."},{"topic":"보안카드","label":"은행 앱 로그인 화면","detail":"비밀번호 입력 후, '보안카드 번호' 입력 창이 나타나는 것을 보고, 다중 인증의 단계를 시각적으로 인식한다."},{"topic":"공동인증서발급","label":"은행 앱 로그인 화면","detail":"로그인 시 '공동인증서 로그인' 옵션이 여전히 가장 높은 보안 수준의 선택지로 제시되는 것을 볼 수 있다."},{"topic":"공동인증서발급","label":"공공기관 웹사이트","detail":"민원 서류 발급 페이지에서 '공동인증서'를 통한 본인 확인 절차가 가장 먼저 안내되는 경우가 많다."},{"topic":"금융인증서","label":"은행 앱 로그인 화면","detail":"로그인 시 '인증서 로그인' 옵션이 가장 눈에 띄는 곳에 배치되어, 사용자가 가장 먼저 이 수단을 떠올리게 한다."},{"topic":"금융인증서","label":"대출 심사 페이지","detail":"대출 신청 시, 신원 확인을 위해 금융인증서 기반의 '전자 서명' 절차를 거치도록 유도하는 과정이 필수적이다."},{"topic":"공인인증서폐지","label":"은행 앱의 로그인 화면","detail":"기존에는 공인인증서 선택지가 눈에 띄었으나, 점차 간편 비밀번호나 생체 인증 버튼만 강조되는 추세가 보인다."},{"topic":"공인인증서폐지","label":"공공기관 웹사이트의 로그인 창","detail":"공인인증서 외에 네이버/카카오 등 간편 로그인 옵션이 기본 옵션으로 자리 잡고 있다."},{"topic":"간편비밀번호","label":"은행 앱 로그인 화면","detail":"비밀번호 입력 창 대신 지문 인식 버튼이나 얼굴 인식 카메라가 전면에 배치되어 있는 것을 통해 간편 인증의 보편화를 알 수 있다."},{"topic":"간편비밀번호","label":"공공 와이파이 사용 후 접속 시","detail":"기기 자체의 인증(예: 기기 ID 기반 로그인)을 요구하는 경우가 늘어나며, 간편 인증이 네트워크 환경과 결합되고 있음을 보여준다."},{"topic":"계좌통합조회","label":"은행 앱의 '통합 조회' 버튼","detail":"대출이나 신용카드 발급 시, 여러 금융사의 정보를 한 번에 조회할 수 있는 기능을 통해 서비스의 필요성을 체감한다."},{"topic":"계좌통합조회","label":"금융 상품 비교 플랫폼","detail":"여러 은행의 금리, 수수료, 조건을 한 화면에서 비교할 수 있게 되어, 개인이 직접 여러 곳을 방문할 필요가 없어졌다."},{"topic":"숨은돈찾기","label":"은행 상품 안내 책자","detail":"상품 설명서의 '예금자보호' 문구와 '세제 혜택' 항목을 통해 해당 상품의 안전성과 세금 구조를 즉각적으로 파악할 수 있다."},{"topic":"숨은돈찾기","label":"재무 상담 기록","detail":"자금의 목적(주택 구매, 은퇴 등)이 명확해질수록, 금융 상품의 종류가 특정 목표에 맞춰 제한적으로 좁혀지는 경향을 보인다."},{"topic":"휴면계좌조회","label":"금융기관의 안내 문자","detail":"주기적으로 '휴면 자산 조회 서비스'를 안내하는 문자가 발송되는 것은, 금융당국이 이 자금의 회수 및 활용을 독려하고 있음을 보여준다."},{"topic":"휴면계좌조회","label":"금융감독원 웹사이트의 공지","detail":"휴면계좌 관련 정책이나 법 개정 사항이 공지되는 것은, 이 자산이 단순한 잔액이 아니라 사회적, 제도적 관심사임을 의미한다."},{"topic":"착오송금반환","label":"은행의 '착오송금 반환 안내' 문자","detail":"은행이 시스템 오류로 인한 착오송금 발생 가능성을 사용자에게 경고하는 문자를 발송하는 경우, 금융기관의 책임 범위가 명확해지는 신호이다."},{"topic":"착오송금반환","label":"금융감독원의 공지사항","detail":"특정 기간 동안 착오송금 피해 사례가 급증할 경우, 감독기관이 임시적인 피해 구제 방안이나 가이드라인을 발표하는 형태로 나타난다."},{"topic":"이체취소","label":"은행 앱의 '거래 내역' 화면","detail":"취소된 거래는 '취소' 또는 '반환' 등의 상태 코드로 표시되며, 이 상태 코드가 거래의 최종 상태를 알려주는 중요한 지표가 된다."},{"topic":"이체취소","label":"피해 구제 안내문","detail":"금융사기 피해 발생 시, '즉시 신고 및 지급정지 요청'을 최우선으로 안내하며 시간적 민감성을 강조한다."},{"topic":"지연이체서비스","label":"계약서상의 지급일 명시","detail":"계약서에 '지급일로부터 30일 이내'와 같이 기간을 명시하는 것 자체가 지연이체와 같은 시간 조정 메커니즘의 필요성을 보여준다."},{"topic":"지연이체서비스","label":"기업 간 대금 결제 요청 메일","detail":"‘자금 상황을 고려하여 다음 달 15일경 입금 부탁드립니다’와 같은 요청은 지연이체와 같은 시간 조정의 필요성을 현실적으로 반영한다."},{"topic":"입금계좌지정","label":"의심 거래 보고서(STR)","detail":"금융기관이 고객의 비정상적인 입금/출금 패턴을 발견했을 때, 자금세탁 가능성을 의심하며 작성하는 내부 보고서이다."},{"topic":"입금계좌지정","label":"대규모 자금 이동 알림","detail":"갑자기 큰 금액이 여러 계좌로 분산되거나, 평소와 다른 패턴으로 입금되는 경우, 금융기관 시스템에서 경고 신호가 발생한다."},{"topic":"비대면계좌개설","label":"모바일 뱅킹 앱의 첫 화면","detail":"계좌 개설 버튼을 누르면 바로 본인 명의의 휴대폰 인증이나 공동인증서 로그인을 요구하는 것이 일반적이다."},{"topic":"비대면계좌개설","label":"지점 방문 전 상담원과의 통화","detail":"복잡한 상품 가입을 위해 비대면으로 상담을 받더라도, 최종적으로는 전화 통화나 화상 통화 등 추가적인 '대면성' 절차가 요구되는 경우가 많다."},{"topic":"계좌개설20일제한","label":"은행 지점 방문 시","detail":"직원에게 신분증과 함께 '자금 사용 목적'을 구두로 설명해야 하는 과정 자체가 계좌개설의 핵심 절차임을 보여준다."},{"topic":"계좌개설20일제한","label":"온라인 금융 서비스 이용 시","detail":"본인 명의의 휴대폰 인증이나 공인인증서 제출을 요구하는 과정은 신원 확인의 디지털화된 증거이다."},{"topic":"한도계좌해제","label":"대형 계약 체결 직후","detail":"부동산 계약금이나 사업 투자금 등 큰 금액이 입금된 직후, 금융기관에서 자금 출처 확인을 위한 추가 서류를 요청하는 경우가 빈번하다."},{"topic":"한도계좌해제","label":"해외 송금 시","detail":"특히 송금 목적지나 금액이 평소와 다를 경우, 금융기관은 자금의 성격과 목적을 상세히 묻는 절차를 거친다."},{"topic":"급여계좌증빙","label":"대출 상담 창구","detail":"직원들이 가장 먼저 '원천징수영수증'이나 '급여통장 사본'을 요청하는 모습에서 증빙의 중요성을 체감할 수 있다."},{"topic":"급여계좌증빙","label":"월급날 직후의 통장 내역","detail":"급여가 입금된 직후의 통장 내역은 해당 소득이 근로를 통해 발생했음을 가장 명확하게 보여주는 증거다."},{"topic":"통장사본출력","label":"대출 상담 창구","detail":"직원들이 가장 먼저 요청하는 서류 중 하나로, 고객의 재정적 배경을 파악하는 가장 기본적인 질문 단계에서 사용된다."},{"topic":"통장사본출력","label":"계약서 작성 시","detail":"임대인이나 사업자가 계약 당사자의 신분과 자금의 투명성을 확인하기 위해 요구하는 필수적인 서류 중 하나로 활용된다."},{"topic":"계좌번호체계","label":"은행 앱의 이체 화면","detail":"이체 시 계좌번호를 입력하는 칸이 반드시 요구되며, 이 숫자가 자금의 최종 목적지를 결정하는 핵심 정보로 작용한다."},{"topic":"계좌번호체계","label":"해외 온라인 쇼핑몰 결제 창","detail":"국가와 은행을 지정하고 SWIFT 코드를 요구하는 과정 자체가 국내와 국제 금융 시스템의 구조적 차이를 보여준다."},{"topic":"SWIFT코드","label":"해외 송금 요청서","detail":"송금받는 계좌 정보와 함께 반드시 SWIFT 코드와 BIC가 요구되는 항목을 통해 그 중요성을 체감할 수 있다."},{"topic":"SWIFT코드","label":"국제 무역 계약서","detail":"대금 결제 조건(Payment Terms)에 SWIFT 코드를 명시하는 것은 거래의 신뢰성과 실행 가능성을 높이는 핵심 요소이다."},{"topic":"IBAN","label":"해외 은행 계좌 개설 서류","detail":"해외 은행에서 계좌를 개설하거나 거래를 할 때, 계좌번호와 함께 IBAN을 필수로 요구하는 것을 볼 수 있다."},{"topic":"IBAN","label":"국제 송금 서비스 웹사이트","detail":"해외 송금 서비스를 이용하는 웹사이트의 입력 필드에 계좌번호와 별도로 IBAN 입력란이 존재하는 것을 통해 그 중요성을 체감할 수 있다."},{"topic":"해외송금방법","label":"해외 온라인 결제 승인 메시지","detail":"결제 금액에 국가별 수수료나 환전 수수료가 포함되어 최종 결제액이 예상보다 높게 책정되는 것을 통해 비용 구조를 체감한다."},{"topic":"해외송금방법","label":"해외 계좌 이체 알림","detail":"송금된 금액이 예상보다 적거나, 수수료 항목이 명확하게 분리되어 청구되는 것을 통해 비용의 투명성을 확인한다."},{"topic":"해외송금수수료","label":"해외 결제 알림 문자","detail":"결제 완료 알림에 '수수료'와 '환전 스프레드'가 각각 분리되어 명시되는 경우, 총 비용을 정확히 파악하기 어렵다는 점을 인지해야 한다."},{"topic":"해외송금수수료","label":"해외 송금 전 비교 사이트","detail":"여러 금융기관의 송금 수수료와 환율을 비교하는 사이트가 존재하지만, 실제 적용되는 '최종 수취액'을 기준으로 비교하는 것이 중요하다."},{"topic":"송금한도신고","label":"은행 창구 직원과의 대화","detail":"대규모 송금 시 직원이 '자금 출처'와 '사용 목적'을 구체적으로 질문하는 것이 가장 흔한 경험이다."},{"topic":"송금한도신고","label":"해외 송금 안내문","detail":"송금액과 함께 '세금 신고' 또는 '자금 출처 증명 서류' 제출 안내가 필수적으로 포함되어 있다."},{"topic":"증빙서류송금","label":"은행 창구 직원과의 대화","detail":"직원이 '송금 목적을 증빙할 서류가 필요합니다'라고 말하는 순간, 모든 절차가 멈추고 서류 준비가 최우선 과제가 된다."},{"topic":"증빙서류송금","label":"해외 송금 서비스 웹사이트","detail":"송금액과 국가를 입력한 후, '필수 첨부 서류' 목록이 자동으로 생성되어 사용자에게 요구되는 증빙의 종류를 알려준다."},{"topic":"외화통장","label":"해외 직구 결제 화면","detail":"결제 시 원화로 결제할지, 외화로 결제할지 선택하게 되는데, 이 선택지가 환율 노출의 크기를 결정한다."},{"topic":"외화통장","label":"해외 주식 거래 계좌","detail":"해외 증권사 계좌를 개설하거나 외화통장을 활용하는 것은, 해당 자산이 외화 기반으로 거래됨을 의미한다."},{"topic":"환전우대율","label":"여행 전 외화 환전 창구","detail":"여러 은행의 환전우대율을 비교하는 전단지나 온라인 공지에서, 우대율이 높을수록 더 많은 혜택을 받는다고 인식하게 만든다."},{"topic":"환전우대율","label":"해외 결제 승인 내역","detail":"실제 결제된 금액에 환전 수수료가 포함되어 청구되므로, 환전우대율이 적용되었는지 여부를 최종 결제 내역에서 확인해야 한다."},{"topic":"수표발행","label":"은행 창구의 수표 처리 시간","detail":"수표를 입금한 후 실제 계좌에 돈이 들어오기까지 걸리는 시간은 은행 간의 자금 이동 및 지급정산 시스템의 작동 속도를 보여준다."},{"topic":"수표발행","label":"수표 부도 통지서","detail":"수표의 지급이 거절되었음을 공식적으로 통보받는 과정은, 결제 수단이 단순한 돈이 아니라 '약속'이었음을 상기시킨다."},{"topic":"자기앞수표","label":"은행 창구의 수표 결제 시간","detail":"오전 중 결제된 수표가 오후에 결제되지 못하는 등, 시스템의 시간적 제약이 실제로 존재함을 체감할 수 있다."},{"topic":"자기앞수표","label":"대형 계약서의 결제 방식 명시","detail":"계약서에 '현금 또는 자기앞수표'와 같이 결제 수단을 명시하는 것은, 자금의 확실성을 최우선으로 고려하기 때문이다."},{"topic":"수표조회","label":"은행 창구의 수표 검사","detail":"수표를 입금할 때 직원이 수표의 발행처, 날짜, 금액 등을 꼼꼼히 확인하는 과정 자체가 시스템의 안전장치를 보여준다."},{"topic":"수표조회","label":"채권 회수 과정","detail":"채무자가 수표를 지급하지 못할 경우, 법적 절차를 통해 수표를 압류하고 부도 처리하는 과정이 실제로 존재한다."},{"topic":"통장정리","label":"월급날 직후의 계좌 잔액","detail":"급여가 들어오자마자 여러 계좌로 돈이 빠져나가고 남은 잔액이 적어 보이는 것이 통장 정리의 가장 명확한 증거이다."},{"topic":"통장정리","label":"자동이체 설정 목록","detail":"매달 고정적으로 빠져나가는 공과금, 대출 상환액, 적금 이체액 등이 목록화되어 재정의 구조를 보여준다."},{"topic":"무통장입금","label":"쇼핑몰 주문 확인 페이지","detail":"결제 완료 후 '가상계좌 번호'와 '입금자명(주문번호 또는 이름)'을 명시적으로 안내하는 것이 가장 흔한 형태이다."},{"topic":"무통장입금","label":"기업의 대금 청구서","detail":"대규모 거래 시, 입금 계좌와 함께 '입금 시 반드시 포함해야 할 참조 번호'를 별도로 강조하여 안내하는 경우가 많다."},{"topic":"가상계좌","label":"온라인 결제 안내 페이지","detail":"결제할 계좌번호와 함께 '주문번호: 12345', '이름: 홍길동'과 같이 입금해야 할 식별 정보가 명확히 제시된다."},{"topic":"가상계좌","label":"은행 앱의 입금 내역 조회","detail":"가상계좌를 통해 입금된 금액이 단순히 '입금'으로만 뜨지 않고, 주문번호나 특정 키워드가 포함되어 분류되어 나타난다."},{"topic":"펌뱅킹","label":"급여 명세서","detail":"매월 급여가 입금되는 날, 수많은 직원 계좌에 동시에 자금이 들어오는 모습은 펌뱅킹의 대표적인 결과물이다."}]