[{"topic":"위험 구역 경고","label":"공사장 안전 펜스","detail":"펜스 자체는 물리적 경계 역할을 하지만, 그 위에 부착된 경고문구는 경계를 넘지 말아야 하는 이유(추락 위험 등)를 반복적으로 상기시킨다."},{"topic":"위험 구역 경고","label":"교차로의 신호등 변화","detail":"빨간불이 켜지는 순간의 시각적 변화는 운전자에게 즉각적인 행동 정지(멈춤)라는 물리적 명령을 내리며 위험을 통제한다."},{"topic":"게임 서버 오류","label":"게임 내 '랙' 현상","detail":"특정 순간에 캐릭터가 멈추거나 움직임이 부자연스러워지는 것은, 서버가 실시간으로 모든 플레이어의 움직임 데이터를 처리하지 못하고 지연시키기 때문이다."},{"topic":"게임 서버 오류","label":"접속 시 '서버 점검' 공지","detail":"실제 오류가 발생했을 때보다, 사전에 점검 시간을 공지하는 것이 사용자들의 심리적 불안감을 낮추고 서비스 신뢰도를 높이는 효과가 크다."},{"topic":"게임 스토리 라인","label":"게임 속 NPC의 반응","detail":"플레이어가 특정 퀘스트를 수행했는지 여부에 따라 NPC가 기억하고 반응하는 대화나 행동 변화는 스토리의 '기억' 메커니즘을 보여준다."},{"topic":"게임 스토리 라인","label":"게임의 엔딩 크레딧","detail":"스토리의 결말을 요약하거나, 다음 작품의 떡밥을 던지는 방식은 현재의 서사를 완결시키고 다음 서사로의 연결고리를 제공한다."},{"topic":"경쟁 게임 플레이","label":"패배 후의 감정적 반응","detail":"패배했을 때 느끼는 분노나 좌절감은 단순히 게임의 결과가 아니라, 자신이 기대했던 '실력'과 '결과' 사이의 괴리에서 비롯된다."},{"topic":"경쟁 게임 플레이","label":"커뮤니티의 '빌드' 공유","detail":"특정 캐릭터나 조합이 강력하다고 알려지면, 플레이어들은 이를 최적화하고 공유하며 집단 지성을 통해 메타를 형성하고 개선한다."},{"topic":"게임 리마스터","label":"게임 스팀(Steam)의 '클래식' 섹션","detail":"오래된 게임들이 꾸준히 재발매되거나 리마스터되는 현상은, 플레이어들이 과거의 경험을 재구매할 의사가 있음을 보여준다."},{"topic":"게임 리마스터","label":"게임 콘솔의 세대교체 주기","detail":"새로운 콘솔이 나올 때마다 구작의 리마스터 버전이 필수로 출시되는 것은, 기술적 격차 해소가 시장의 주요 동력임을 증명한다."},{"topic":"화상 등급 및 처치","label":"화상 환자 이송 차량","detail":"화상 환자는 체온 저하와 쇼크 위험이 높아, 일반 이송보다 체온 유지 장비와 순환 모니터링 장비가 필수적으로 갖춰져 있다."},{"topic":"화상 등급 및 처치","label":"병원 응급실의 화상 처치 구역","detail":"대형 화상 환자를 위해 넓은 공간에 여러 개의 드레싱 세트와 수액 공급 라인이 준비되어 있는 것이 관찰된다."},{"topic":"질식 시 대처법","label":"식당이나 공공장소","detail":"사람이 갑자기 손으로 목을 감싸거나, 말을 할 수 없이 기침만 하는 모습을 목격할 수 있다."},{"topic":"질식 시 대처법","label":"CPR 교육 현장","detail":"실제 마네킹을 이용해 압박의 깊이와 속도를 몸으로 익히는 훈련이 필수적으로 진행된다."},{"topic":"실종자 수색 절차","label":"수색 현장의 통제 구역 설정","detail":"수색팀이 활동하는 구역 주변에 출입 통제선이나 경계 표시가 명확하게 설치되어 있는 것을 볼 수 있다. 이는 자원 낭비와 정보 누수를 막기 위함이다."},{"topic":"실종자 수색 절차","label":"다층적인 정보 분석 회의","detail":"수사관들이 지도, 통신 기록 그래프, 목격자 진술 등을 여러 자료 위에 겹쳐놓고 토론하는 모습에서, 정보 간의 교차 검증이 이루어지고 있음을 알 수 있다."},{"topic":"교통 법규 위반 시 벌점","label":"교통 위반 통지서","detail":"벌점과 함께 명시된 '누적 점수'는 운전자가 자신의 행동이 미래의 운전 권한에 직접적인 영향을 미치고 있음을 시각적으로 인지하게 만든다."},{"topic":"교통 법규 위반 시 벌점","label":"면허 정지 안내문","detail":"벌점 시스템의 최종적인 결과가 단순한 벌금이 아니라, 일정 기간 동안 운전 자체를 할 수 없게 만드는 '기회 박탈'임을 보여준다."},{"topic":"비상구 피난 경로","label":"건물 출입구의 안내 표지판","detail":"비상구와 피난 방향을 나타내는 표지판이 주 통로와는 다른 위치에, 그리고 일관된 색상으로 부착되어 있다."},{"topic":"비상구 피난 경로","label":"지하철역의 대피 안내 방송","detail":"화재 발생 시, 단순히 '대피하세요'를 넘어 구체적인 대피 방향과 경로를 단계적으로 안내한다."},{"topic":"재해 복구 계획 수립","label":"대규모 정전 사태 이후의 모습","detail":"전기 공급이 끊기자마자 통신망이 마비되고, 결국 오프라인 커뮤니티와 비상 발전기 같은 물리적 자원의 중요성이 부각된다."},{"topic":"재해 복구 계획 수립","label":"재난 지역의 임시 거주지","detail":"정부나 기업의 공식적인 지원이 닿지 않는 사각지대에서, 이웃 간의 자발적인 도움과 협력이 가장 먼저 생존의 동력이 된다."},{"topic":"산사태 발생 시 대피","label":"산사태 경고 방송","detail":"지진이나 폭우가 잦은 지역에서 갑작스럽게 울리는 경고 방송은 즉각적인 대피를 명령하는 가장 중요한 신호이다."},{"topic":"산사태 발생 시 대피","label":"토사 유출물","detail":"도로변이나 계곡에서 갑자기 흙과 돌이 섞인 물줄기가 발견된다면, 이는 산사태가 임박했음을 알리는 물리적 징후이다."},{"topic":"산사태 발생 시 대피","label":"지반의 균열","detail":"평소와 달리 땅바닥에 크고 깊은 균열이 발생하거나, 건물 기초가 기울어 보인다면 지반 침하가 진행 중일 수 있다."},{"topic":"소화기 사용법 종류","label":"소화기 비치 위치","detail":"주요 통로나 위험 구역에 소화기가 눈에 잘 띄게 배치되어 있는 것은 안전 의식이 작동하고 있음을 보여준다."},{"topic":"소화기 사용법 종류","label":"소화기 사용 후 잔여 분말","detail":"소화기 사용 후 바닥에 떨어진 분말은 화재가 완전히 진압되었음을 의미하는 것이 아니라, 추가적인 위험 요소를 내포할 수 있다."},{"topic":"산업 안전 기준","label":"공사 현장의 안전 펜스","detail":"단순한 경계 표시를 넘어, 추락 위험 구역을 물리적으로 차단하는 구조물 자체가 안전 기준의 물리적 구현 사례이다."},{"topic":"산업 안전 기준","label":"산업용 기계의 비상 정지 버튼","detail":"작업자가 위험을 감지했을 때, 복잡한 절차를 거치지 않고 즉각적으로 시스템을 멈출 수 있게 하는 가장 기본적인 안전장치이다."},{"topic":"화학 물질 안전 데이터시트(MSDS)","label":"작업장 비치된 안전 게시판","detail":"최근 사용된 화학물질의 MSDS가 최신 버전으로 교체되어 붙어 있는 것을 통해, 해당 사업장이 안전 관리 시스템을 주기적으로 업데이트하고 있음을 보여준다."},{"topic":"화학 물질 안전 데이터시트(MSDS)","label":"개인보호구(PPE) 착용 지침","detail":"특정 구역에 진입할 때마다 해당 구역의 MSDS에 명시된 적정 방독면과 보호복을 착용하는 모습은, 위험성 인지 기반의 통제 절차가 작동하고 있음을 보여준다."},{"topic":"건축물 구조 안전 점검","label":"건물 외벽의 미세한 수직 균열","detail":"단순한 미관상의 문제로 치부하기 쉽지만, 균열의 진행 방향과 폭 변화는 구조체 내부의 응력 집중이나 변형을 의미할 수 있다."},{"topic":"건축물 구조 안전 점검","label":"지하 주차장 바닥의 기울어짐","detail":"지반의 침하가 구조물 전체에 영향을 미치기 시작했다는 초기 신호일 수 있으며, 이는 건물 전체의 수평 변위로 이어질 위험이 있다."},{"topic":"취약 계층 보호 수칙","label":"재난 대비 키트","detail":"단순한 물품 구비 외에, 만성질환 약물, 개인별 복용 스케줄, 응급 연락망 등이 포함된 '개인화된' 키트가 필수적이다."},{"topic":"취약 계층 보호 수칙","label":"요양 시설의 비상 대피 훈련","detail":"시설 내 거동이 불편한 거주자를 안전하게 이동시키기 위해 전담 인력과 장비가 동원되는 훈련이 주기적으로 이루어진다."},{"topic":"게임 시나리오","label":"게임의 컷신(Cutscene) 연출","detail":"주요 스토리 전개 구간에서 갑자기 게임 플레이가 멈추고 연출에 집중하는 것은, 플레이어에게 '지금은 시스템보다 이야기에 집중하라'는 서사적 신호를 보내는 행위이다."},{"topic":"게임 시나리오","label":"NPC의 대화 변화","detail":"특정 스토리 분기점을 거치거나 중요한 사건을 겪은 캐릭터가 이전과 다른 태도나 지식을 보여주는 것은, 캐릭터 아크가 성공적으로 작동했음을 보여주는 가장 명확한 신호이다."},{"topic":"여성 응급 상황","label":"응급실 방문 기록지","detail":"진료 기록에 '출혈 원인 불명' 또는 '산부인과적 응급 상황'으로 분류된 경우가 많아, 원인 파악의 어려움을 보여준다."},{"topic":"여성 응급 상황","label":"산부인과 응급실의 혼잡도","detail":"월경 기간이 아닌데도 출혈이나 하복부 통증을 호소하는 환자가 많아, 비응급 상황과 응급 상황의 구분이 모호할 때가 많다."},{"topic":"여성 응급 상황","label":"응급 키트 구성품","detail":"일반적인 외상용품 외에, 임신 가능성 테스트기나 산부인과 관련 응급 처치 물품이 포함되는 경우가 늘고 있다."},{"topic":"비상 탈출구","label":"건물 복도의 안내 표지판","detail":"비상구와 피난 방향을 지시하는 표지판의 높이, 밝기, 그리고 반복적인 위치 배치는 안전 기준의 물리적 구현을 보여준다."},{"topic":"비상 탈출구","label":"대피 훈련 안내문","detail":"건물 입구 등에 부착된 대피 요령 포스터는 실제 위기 상황에 대비하여 행동 지침을 사전에 숙지하도록 유도한다."},{"topic":"스킨 커스터마이징","label":"패션 브랜드의 한정판 콜라보","detail":"특정 시기에만 판매하는 콜라보레이션 제품은 '지금 아니면 못 가진다'는 희소성 원칙을 통해 구매 욕구를 극대화한다."},{"topic":"스킨 커스터마이징","label":"SNS 프로필 꾸미기","detail":"사용자들이 프로필 사진, 배지, 테마 등을 꾸미는 행위는 가상 세계에서 자신의 정체성을 표현하려는 본능적인 욕구의 발현이다."},{"topic":"대리 육성","label":"게임 튜토리얼 모드","detail":"게임 초반에 특정 미션을 따라가며 시스템의 작동 원리를 배우는 과정 자체가 대리 육성의 가장 흔한 예시다."},{"topic":"대리 육성","label":"신입사원 온보딩 프로그램","detail":"회사에 처음 입사한 직원이 선배의 도움을 받아 업무 프로세스를 익히는 과정은 직장 생활의 대리 육성 과정이다."},{"topic":"위험물 처리","label":"안전 표지판과 경고문","detail":"현장에서 발견되는 '위험', '주의' 등의 표지판은 해당 물질이 가진 잠재적 위험성을 시각적으로 경고하는 가장 기본적인 안전장치이다."},{"topic":"위험물 처리","label":"방독면과 보호복 착용","detail":"유해 물질을 다루는 작업자가 보호 장비를 착용하는 모습은, 위험물 노출을 막기 위한 물리적 격리가 필수적임을 보여준다."},{"topic":"화재감지기 점검","label":"건물 관리실의 점검표","detail":"점검 항목에 '감지기 청소 및 작동 테스트'가 필수적으로 기재되어 있는 것을 볼 수 있다."},{"topic":"화재감지기 점검","label":"화재 경보 시스템의 주기적 테스트","detail":"특정 시간대에 건물 전체의 경보음이 울리는 것은 시스템의 정상 작동 여부를 확인하는 과정이다."},{"topic":"재난 문자 대응","label":"재난 방송의 반복적인 송출","detail":"특정 재난 발생 시, TV나 라디오가 반복적으로 같은 정보를 송출하는 것은 정보의 중요성과 긴급성을 강조하는 방식이다."},{"topic":"재난 문자 대응","label":"지역 커뮤니티의 비상 연락망 구축","detail":"재난 발생 후 공식 통신망이 마비되면, 이웃 간의 자발적인 연락망이 가장 중요한 생존 정보 통로가 된다."},{"topic":"스미싱 방지","label":"택배 배송 알림 문자","detail":"주소지나 이름이 정확하게 언급되어 있어 신뢰도가 높아지지만, 링크를 통해 개인 정보를 요구할 때는 항상 의심해야 한다."},{"topic":"스미싱 방지","label":"공공기관의 긴급 안내 문자","detail":"재난 상황 등 긴급 상황에서 오는 문자는 신뢰도가 높지만, 출처가 불분명한 경우에도 반드시 공식 채널을 통해 교차 확인해야 한다."},{"topic":"사이버 보안 수칙","label":"출처 불명의 첨부 파일","detail":"업무 관련처럼 위장한 이메일의 첨부 파일은 악성코드를 포함하고 있을 가능성이 높으므로, 열기 전에 발신자를 반드시 재확인해야 한다."},{"topic":"사이버 보안 수칙","label":"로그인 실패 알림","detail":"여러 번의 로그인 실패 알림이 반복된다면, 계정 정보가 해킹 시도에 노출되었을 가능성을 의심하고 즉시 비밀번호를 변경해야 한다."},{"topic":"사이버 보안 수칙","label":"공공장소의 PC 사용","detail":"공공장소의 PC를 사용한 후에는 반드시 로그아웃하고, 개인 정보가 담긴 창은 닫는 습관이 필요하다."},{"topic":"정수기 관리","label":"정수기 필터 교체 알림등","detail":"사용량 기반의 교체 알림은 단순히 시간이 지났다는 의미가 아니라, 필터가 처리할 수 있는 오염물질의 한계치에 도달했음을 시사한다."},{"topic":"정수기 관리","label":"물맛의 갑작스러운 변화","detail":"물맛의 변화는 필터 막힘이나 내부 배관의 오염이 시작되었다는 가장 직관적이고 초기적인 경고 신호일 수 있다."},{"topic":"생활방수","label":"곰팡이가 핀 벽지","detail":"습기가 벽 내부로 침투하여 결로 현상과 함께 곰팡이 포자를 번식시키는 가장 흔한 생활 방수의 실패 신호이다."},{"topic":"생활방수","label":"벽면의 백화 현상","detail":"콘크리트 내부의 염분이나 수분이 표면으로 이동하며 하얀 가루(백화)를 만들 때, 이는 방수층의 기능 저하를 의미할 수 있다."},{"topic":"소방차 이용 방법","label":"화재 발생 현장의 교통 통제","detail":"소방차의 접근을 위해 주변 차량이 일시적으로 우회하거나 주차 공간이 확보되는 모습에서 우선순위가 드러난다."},{"topic":"소방차 이용 방법","label":"소방차의 특수 장비 전개","detail":"화재 현장에서 호스를 펼치거나 사다리를 설치하는 과정은 단순한 이동이 아닌, 체계적인 작업 과정임을 보여준다."},{"topic":"랜덤 드롭 아이템","label":"뽑기 기계(Gacha)","detail":"원하는 캐릭터나 아이템을 얻기 위해 반복적으로 돈을 투입하는 행위 자체가 랜덤 드롭 시스템의 가장 직접적인 현실적 구현이다."},{"topic":"랜덤 드롭 아이템","label":"스포츠 경기의 승패 예측","detail":"경기 결과가 불확실한 상황에서 베팅을 통해 기대 수익을 얻으려는 심리가 랜덤 드롭 시스템의 심리와 유사하다."},{"topic":"티어 매치 시스템","label":"초반 매칭의 난이도","detail":"새로운 플레이어가 처음 접하는 매칭 게임에서, 초반 몇 판은 실력 차이가 크게 느껴지는 경향이 있다."},{"topic":"티어 매치 시스템","label":"레이팅 하락 후의 심리","detail":"레이팅이 급격히 떨어지기 시작하면, 플레이어는 실력과 무관하게 게임에 대한 흥미를 잃고 접속 빈도가 줄어든다."},{"topic":"게임 시스템의 재미 요소","label":"직장 내 성과 평가 시스템","detail":"목표 설정(Goal Setting)과 그에 따른 보상(Bonus) 구조는 게임의 '성장 곡선'과 '피드백 루프'의 현실적 유사체이다."},{"topic":"게임 시스템의 재미 요소","label":"취미 활동의 루틴화","detail":"새로운 기술을 배우거나 취미를 반복할 때 느끼는 작은 성취감(레벨업)이 지속적인 동기 부여를 제공한다."},{"topic":"감전 안전거리","label":"공사 현장의 안전 표지판","detail":"전선 근처에 '접근 금지', '안전거리 유지' 등의 경고 표지판이 설치되어 작업자에게 물리적 경계를 시각적으로 알린다."},{"topic":"감전 안전거리","label":"누전 차단기 작동","detail":"작은 누설 전류가 감지되어 차단기가 떨어지는 현상은, 안전거리 확보가 실패했을 때 시스템이 작동하는 방어 기제이다."},{"topic":"응급의료정보시스템 사용법","label":"응급실의 전산 기록지","detail":"시스템 화면에 여러 정보가 동시에 떠 있지만, 의료진은 가장 중요한 활력징후와 알레르기 정보에만 시선이 집중되는 경향을 보인다."},{"topic":"응급의료정보시스템 사용법","label":"구급대원 간의 구두 인계","detail":"시스템이 완벽하지 않은 상황에서, 구두로 전달되는 환자 상태 변화나 특이사항이 가장 중요한 정보가 되기도 한다."},{"topic":"산업 현장 안전장비","label":"안전모와 안전화","detail":"현장에 들어서는 순간 가장 먼저 착용하는 장비로, 안전 의식의 최소한의 기준을 시각적으로 보여준다."},{"topic":"산업 현장 안전장비","label":"작업장 내 경고 표지판","detail":"특정 구역이나 장비 사용 시 위험성을 시각적으로 경고하며, 안전 절차의 시작점을 알려준다."},{"topic":"차량 전복 예방","label":"빗길의 차선 변경","detail":"평소보다 훨씬 느리고 부드럽게 조향하며, 차선 변경 시에도 급격한 가속이나 제동을 삼가게 된다."},{"topic":"차량 전복 예방","label":"고속도로의 코너링","detail":"코너 진입 전 속도를 미리 줄이고, 코너를 빠져나갈 때까지 일정한 속도를 유지하려는 경향을 보인다."},{"topic":"로그 분석 방법","label":"운영팀의 '로그 분석' 요청","detail":"특정 장애가 발생했을 때, '로그 좀 봐달라'는 요청은 사실상 '이 로그 데이터에서 원인을 찾아달라'는 데이터 분석 요청이다."},{"topic":"로그 분석 방법","label":"서비스 장애 공지","detail":"공지된 장애 원인이 '로그 분석 결과'를 통해 최종적으로 확정되는 경우가 많다."},{"topic":"수익 모델 구조","label":"구독 서비스의 등장","detail":"넷플릭스나 스포티파이처럼, 콘텐츠를 소유하는 대신 정기적인 비용을 지불하고 지속적으로 접근하는 형태가 일반화되고 있다."},{"topic":"수익 모델 구조","label":"게임 내 아이템 판매","detail":"게임의 재미를 해치지 않는 선에서, 캐릭터의 외형이나 편의성을 높이는 아이템을 유료로 판매하는 것이 주요 수익원이다."},{"topic":"개발 주기 이해","label":"베타 테스트 버전의 출시","detail":"제품이 완성되기 전, 일부 사용자에게만 기능을 공개하는 것은 개발 주기를 단축하고 실제 사용 환경에서의 검증을 시도하는 대표적인 예시다."},{"topic":"개발 주기 이해","label":"CI/CD 파이프라인 구축","detail":"코드 변경 사항을 자동으로 테스트하고 배포하는 시스템은 개발 주기를 극단적으로 짧게 만들어, 위험을 최소화하며 지속적인 개선을 가능하게 한다."},{"topic":"콜라보레이션 전략","label":"팝업 스토어의 테마","detail":"특정 캐릭터나 IP가 다른 브랜드의 제품과 결합된 팝업 스토어는, 그 자체로 '한정판 경험'이라는 희소성을 부여하며 구매를 유도한다."},{"topic":"콜라보레이션 전략","label":"게임 캐릭터 상품화","detail":"게임 캐릭터가 의류나 생활용품으로 상품화될 때, 단순한 디자인 재현을 넘어 캐릭터의 서사적 배경이 스토리로 녹아들 때 팬들의 지지를 얻는다."},{"topic":"치트 엔진 작동법","label":"온라인 게임의 갑작스러운 패치","detail":"게임사가 치트 방지 시스템을 업데이트할 때, 메모리 주소 구조 자체를 변경하는 경우가 많아지며, 이는 치트 엔진 사용의 난이도를 급격히 높인다."},{"topic":"치트 엔진 작동법","label":"게임의 '네트워크 동기화' 시스템","detail":"클라이언트 측에서 값을 조작하더라도, 서버가 최종 권한을 가지므로, 클라이언트의 메모리 조작은 서버의 검증 로직에 의해 무효화된다."},{"topic":"최적화 개념","label":"내비게이션 경로 안내","detail":"최단 시간 또는 최단 거리라는 목적 함수를 만족시키기 위해, 실시간 교통량(제약 조건)을 반영하여 가장 효율적인 경로를 계산한다."},{"topic":"최적화 개념","label":"주식 포트폴리오 구성","detail":"최대 수익(목적 함수)을 얻으면서도, 특정 위험 수준(제약 조건)을 초과하지 않도록 자산 배분을 결정하는 과정이다."},{"topic":"화재 발생 시 초기 대응","label":"비상구 유도등","detail":"정전 상황에서도 녹색 빛을 유지하며 가장 안전한 탈출 방향을 시각적으로 알려주는 필수 안전 시설이다."},{"topic":"화재 발생 시 초기 대응","label":"소화전 함","detail":"화재 발생 시 건물 내부의 소방 설비와 연계되어 초기 진압을 위한 물 공급원 역할을 한다."},{"topic":"야생 동물 접촉 위험","label":"쓰레기통 주변의 동물 무리","detail":"인간이 무심코 버린 음식물 쓰레기는 야생동물에게 '쉽게 얻을 수 있는 고칼로리 자원'이라는 잘못된 학습을 심어준다."},{"topic":"야생 동물 접촉 위험","label":"야생동물 출몰 경고 표지판","detail":"이 표지판은 단순히 위험을 알리는 것을 넘어, 인간에게 '현재 이 지역은 야생동물의 생존 영역'이라는 경계를 상기시킨다."},{"topic":"해독제 종류 및 사용","label":"응급실의 독극물 치료 구역","detail":"다양한 색상과 라벨이 붙은 해독제 약물들이 비치되어 있으며, 독소 종류별 프로토콜이 게시되어 있다."},{"topic":"해독제 종류 및 사용","label":"독극물 노출 환자의 초기 검사","detail":"혈액 가스 분석이나 특정 효소 수치 측정 등, 독소의 영향을 받은 신체 시스템의 기능을 정량적으로 확인하는 과정이 필수적이다."},{"topic":"차량 견인차 호출","label":"고속도로 갓길의 안전 표지판","detail":"고장이나 사고가 발생할 수 있는 위험 구역임을 시각적으로 경고하며, 안전한 대피 공간을 확보하도록 유도한다."},{"topic":"차량 견인차 호출","label":"보험사 긴급출동 앱","detail":"위치 기반 서비스(GPS)를 통해 현재 위치와 필요한 도움의 종류를 즉각적으로 전송할 수 있게 한다."},{"topic":"폭우 대비 행동 수칙","label":"하천 주변의 물놀이객","detail":"물살이 거세지거나 수위가 급격히 높아지면, 경고 표지판이나 안내 방송을 무시하고 접근하는 경우가 많다."},{"topic":"폭우 대비 행동 수칙","label":"지하 주차장이나 반지하 거주지","detail":"폭우가 내린 후, 물이 차오르는 것을 보고도 '잠시 지나갈 것'이라 판단하여 대피하지 않는 위험한 상황이 발생한다."},{"topic":"캐리력","label":"경기 중 팀원 간의 소통","detail":"위기 상황에서 누가 먼저 정확한 정보를 제공하고, 그 정보가 전술적 움직임의 결정적인 계기가 될 때."},{"topic":"캐리력","label":"패치 노트의 변화","detail":"특정 캐릭터의 핵심 능력이 너프되거나 버프될 때, 해당 캐릭터의 '캐리력'에 대한 커뮤니티의 논의가 폭발적으로 증가한다."},{"topic":"미드 라이너","label":"경기 중 실시간 채팅창","detail":"미드 라이너가 '갱킹 각'이나 '라인 관리'에 대한 판단을 내리며 팀원들에게 전술적 지시를 내리는 모습에서 그 중요성을 확인할 수 있다."},{"topic":"미드 라이너","label":"경기 후 분석 영상","detail":"전문 해설가들이 미드 라이너의 특정 움직임(예: 와딩 위치, 스킬 사용 타이밍)을 분석하며 승패의 결정적 요인으로 지적하는 경우를 통해 그 중요성을 파악할 수 있다."},{"topic":"탑 라인전","label":"게임 내 미니맵의 시야 변화","detail":"라인전 중 상대방이 예상치 못한 방향에서 시야를 확보하거나, 아군이 시야를 장악하는 순간부터 주도권이 급격히 변하는 것을 체감할 수 있다."},{"topic":"탑 라인전","label":"챔피언의 스킬 이펙트와 쿨타임","detail":"실제 게임 플레이 중 스킬이 사용된 직후의 쿨타임 애니메이션을 확인하며, 다음 스킬 사용을 계획하는 것이 가장 기본적인 판단 기준이 된다."},{"topic":"서포터 조합","label":"경기 중 팀원 간의 포지셔닝 변화","detail":"한 팀의 서포터가 평소에는 후방에 머물다가, 위기 상황에서 전방으로 나와 적을 끌어당기는 등 역할이 유동적으로 변하는 모습."},{"topic":"서포터 조합","label":"경기 전 조합 발표 및 분석","detail":"팀들이 상대 팀의 핵심 챔피언을 카운터하기 위해 특정 조합을 선택하고, 그 이유를 분석하는 과정."},{"topic":"프로 경기 분석","label":"경기 중계 해설의 톤 변화","detail":"경기 초반에는 '데이터상으로는'이라는 객관적 분석이 주를 이루다가, 결정적인 순간에는 '직감적으로', '감으로' 같은 표현이 나오는 지점."},{"topic":"프로 경기 분석","label":"패치 노트 발표 직후의 팀 전술 변화","detail":"새로운 챔피언이나 아이템이 등장하면, 기존에 성공했던 전술이 갑자기 무용지물이 되면서 팀 전술이 급격히 재편성되는 모습."},{"topic":"롤 전술","label":"경기 중 팀원들의 핑 사용","detail":"특정 지역에 대한 '위험' 또는 '집결' 핑을 주고받는 행위 자체가 실시간 전술적 의사소통의 핵심 증거이다."},{"topic":"롤 전술","label":"오브젝트 주변의 교전 발생","detail":"바론이나 드래곤 같은 주요 오브젝트 주변에 전투가 집중되는 것은, 그 오브젝트가 전술적 목표물로 인식되었음을 보여준다."},{"topic":"AP 딜러","label":"테마파크의 캐릭터 코스튬","detail":"단순히 캐릭터를 재현하는 것을 넘어, 특정 상황에 맞춰 감정 변화나 즉흥적인 상호작용을 보여주며 몰입도를 높인다."},{"topic":"AP 딜러","label":"라이브 스트리밍의 전문 진행자","detail":"기술적인 장비 설명이나 규칙 안내를 할 때도, 시청자의 흥미를 잃지 않도록 유머나 개인적인 해석을 섞어 전달한다."},{"topic":"AD 탱커","label":"게임 내 포지셔닝","detail":"전투가 시작될 때 탱커가 가장 먼저 적의 공격을 받아내며 전방에 위치하는 모습은, 그가 전장의 최전선 통제권을 쥐고 있음을 시각적으로 보여준다."},{"topic":"AD 탱커","label":"팀 조합 공지","detail":"팀 조합 설명에서 '이니시에이터'나 '탱커'라는 역할군이 명시되는 것은, 해당 캐릭터가 전술적 시작점(Starting Point)을 담당함을 의미한다."},{"topic":"정글링 효율","label":"경기 중 정글러의 움직임","detail":"정글러가 몬스터를 사냥하는 모습이 아니라, 상대 라이너의 움직임을 따라 이동하며 압박하는 모습이 더 자주 포착된다."},{"topic":"정글링 효율","label":"경기 분석 방송","detail":"전문 해설가들이 '지금은 정글링보다 바텀 압박이 더 중요하다'와 같이 자원 획득의 우선순위를 끊임없이 논한다."},{"topic":"라인 스왑","label":"국가 간 금융 협정","detail":"국가들이 외환 위기 시 상호 간의 금융 지원을 약속하는 협정 자체가 라인 스왑의 개념적 확장으로 볼 수 있다."},{"topic":"라인 스왑","label":"대형 기업의 공급망 금융","detail":"대기업이 협력업체의 부도 위험을 보증하거나 보험 형태로 분담하는 구조는 라인 스왑의 실물 경제적 구현 사례이다."},{"topic":"최애 챔피언","label":"경기 중 챔피언 교체 언급","detail":"해설진이 '최애'라는 단어 대신 '상황에 맞는 챔피언'을 언급하며 유연한 대처를 강조할 때."},{"topic":"최애 챔피언","label":"패치 직후 챔피언 사용률 변화","detail":"특정 챔피언의 성능 변화가 발생하면, 기존의 최애 챔피언이 갑자기 사용률이 급감하거나 폭증하는 현상."},{"topic":"킬 관여도","label":"경기 후 인터뷰","detail":"해설진이 특정 선수의 '개인 활약'을 언급하며 킬 관여도를 높이 평가할 때 자주 사용된다."},{"topic":"킬 관여도","label":"랭크 게임 팀원 간의 대화","detail":"자신의 플레이가 팀 승리에 결정적이었다고 주장하며 킬 관여도를 근거로 제시할 때 사용된다."},{"topic":"익사 사고 대처","label":"물놀이장 안전 요원 배치","detail":"사람이 많이 모이는 물놀이 시설에는 전문 구조 인력이 상주하며 감시하는 모습이 보인다."},{"topic":"익사 사고 대처","label":"구명조끼 착용 의무화","detail":"어린이 물놀이 시 구명조끼를 착용하는 것이 습관화되어 있으며, 이는 부력 확보의 가장 기본적인 예방책이다."},{"topic":"어지러움 대처","label":"엘리베이터에서 내릴 때","detail":"수직 이동 후 갑자기 바닥에 발을 디딜 때 순간적으로 어지러움을 느끼는 것은 혈압 조절의 순간적인 실패를 보여준다."},{"topic":"어지러움 대처","label":"장거리 운전 중","detail":"지루함이나 집중력 저하가 누적되면 혈압 변화에 대한 인지 능력이 떨어져 어지러움을 느끼기 쉽다."},{"topic":"위장 장애","label":"아침 식사 후의 불편함","detail":"밤새 공복 상태를 유지한 위산이 아침 식사 직후에 갑자기 자극을 받으며 속쓰림을 유발하는 경우가 흔하다."},{"topic":"위장 장애","label":"긴장된 상황에서의 복통","detail":"시험이나 발표 등 심리적으로 긴장되는 상황에서 갑작스럽게 배가 아프거나 설사를 하는 경험은 장의 민감도가 높음을 보여준다."},{"topic":"게임 빌드","label":"커뮤니티의 빌드 토론","detail":"패치 직후, 유저들이 가장 먼저 특정 아이템이나 스킬의 효율성을 두고 논쟁하는 모습에서 빌드 변화의 흐름을 읽을 수 있다."},{"topic":"게임 빌드","label":"프로게이머의 경기 중 표정 변화","detail":"상대 팀의 예상치 못한 조합이나 플레이에 대응하여 빌드를 수정해야 할 때, 플레이어의 집중력과 판단력이 극도로 높아진다."},{"topic":"게임 몬스터 디자인","label":"보스전의 패턴 공지","detail":"게임 내에서 '다음 공격은 광역기입니다'와 같은 경고 메시지가 뜨는 것은, 몬스터의 행동을 예측 가능하게 만들어 플레이어에게 대응 기회를 제공하는 핵심 장치이다."},{"topic":"게임 몬스터 디자인","label":"특정 속성 상성 시스템","detail":"불 속성 몬스터가 물 속성 캐릭터에게 약점을 보이도록 설정하는 것은, 몬스터의 디자인을 단순한 힘의 비교가 아닌 '규칙 기반의 상호작용'으로 확장하는 방식이다."},{"topic":"화기구 사용 안전수칙","label":"가스레인지 주변의 젖은 행주","detail":"화재 위험이 높은 구역에 물기나 기름기가 있는 물건을 방치하는 것은, 작은 스파크에도 큰 화재로 번질 수 있는 잠재적 위험을 보여준다."},{"topic":"화기구 사용 안전수칙","label":"소화기 비치 위치의 가림막","detail":"소화기가 눈에 잘 띄지 않거나 사용법이 잊혀진 위치에 방치되어 있다면, 위기 상황에서 가장 중요한 초기 대응 수단이 무용지물이 될 수 있다."},{"topic":"화기구 사용 안전수칙","label":"겨울철 난방기구의 과열된 전선","detail":"전기장판이나 히터 등의 전선이 과도하게 늘어나거나 꺾여져 있다면, 과부하 및 단락으로 인한 화재 위험이 매우 높음을 시각적으로 보여준다."},{"topic":"쓰레기 분리배출법","label":"재활용 분리수거함의 혼재된 내용물","detail":"같은 플라스틱함에 내용물이 섞여 있거나, 재질이 다른 제품이 함께 배출되는 모습은 분류 시스템의 취약점을 보여준다."},{"topic":"쓰레기 분리배출법","label":"재활용품 수거 차량의 적재함","detail":"수거된 재활용품이 현장에서 다시 분류되거나, 오염물질 때문에 폐기물과 섞이는 장면은 공정의 어려움을 시사한다."},{"topic":"캠핑장 안전 규칙","label":"캠핑장 입구 안내판","detail":"화기 사용 금지 구역, 쓰레기 분리수거 요일 등 기본적인 안전 및 환경 수칙이 명시되어 있다."},{"topic":"캠핑장 안전 규칙","label":"취사 공간의 연기","detail":"환기 시설이 미흡하거나 불완전한 화기 사용은 일산화탄소 중독 등 보이지 않는 위험을 초래할 수 있다."},{"topic":"화재 발생 시 신고","label":"비상구 안내 표지판","detail":"화재 위험이 높은 장소에서 가장 먼저 눈에 띄는 구조물이며, 비상 대피 경로의 존재를 시각적으로 상기시켜준다."},{"topic":"화재 발생 시 신고","label":"화재 경보 시스템의 작동음","detail":"일상적인 소음과 구분되는 특정한 패턴의 경보음은 사람들에게 위험 상황임을 즉각적으로 인지시키고 행동을 유발한다."},{"topic":"게임 아트 컨셉","label":"게임 트레일러의 첫 장면","detail":"트레일러 초반에 보여주는 배경이나 캐릭터의 분위기, 색감은 개발팀이 설정한 '아트 컨셉'이 가장 강력하게 반영된 결과물이다."},{"topic":"게임 아트 컨셉","label":"게임의 UI/UX 디자인","detail":"컨셉 아트가 캐릭터나 배경에 집중하는 경향이 있지만, 실제 게임의 인터페이스(UI) 역시 세계관의 톤 앤 매너를 유지하며 컨셉을 이어가야 한다."},{"topic":"경쟁 게임 심리전","label":"경기 중의 과도한 리액션","detail":"실제 게임에서 특정 플레이가 성공했을 때 과장된 기쁨이나 좌절을 보이는 것은, 그 행동이 상대방의 심리적 동요를 유발하려는 시도이다."},{"topic":"경쟁 게임 심리전","label":"경기 전의 심리적 분위기","detail":"경기 전 인터뷰나 훈련 과정에서 상대 팀을 깎아내리거나 심리적으로 압박하는 발언은, 이미 심리전을 시작했음을 보여준다."},{"topic":"프로 게이머 계약 제도","label":"계약 만료 시점의 선수 활동","detail":"계약 만료가 다가올수록 선수가 개인 방송이나 유튜브 등 외부 활동을 늘리며 자신의 IP를 미리 구축하려는 움직임이 관찰된다."},{"topic":"프로 게이머 계약 제도","label":"대형 스폰서십 발표","detail":"구단 차원의 스폰서십 발표와 별개로, 특정 선수가 개인 브랜드로 대형 광고 계약을 체결하는 사례가 늘어나고 있다."},{"topic":"게임 커뮤니티 형성 과정","label":"커뮤니티의 '금기어' 목록","detail":"특정 단어나 주제가 금지어 처리되는 것은, 그 커뮤니티가 공유하는 암묵적인 규범과 경계를 시각적으로 보여주는 가장 명확한 증거이다."},{"topic":"게임 커뮤니티 형성 과정","label":"신규 유저 환영 게시판의 분위기","detail":"새로운 사용자가 어떤 방식으로 환영받거나, 혹은 어떤 질문을 던지면 비판받는지를 통해 커뮤니티의 문화적 수용도가 파악된다."},{"topic":"베인 상처 소독","label":"병원 상처 드레싱","detail":"최근에는 소독액을 붓는 방식보다, 습윤한 거즈나 하이드로콜로이드 드레싱을 사용하는 추세가 늘고 있다."},{"topic":"베인 상처 소독","label":"응급실의 초기 처치","detail":"출혈이 심하거나 이물질이 의심될 경우, 소독제 사용보다는 깨끗한 물이나 생리식염수로 세척하는 것이 우선된다."},{"topic":"재난 심리 안정","label":"지인 간의 위로 대화","detail":"상대방의 말을 끊지 않고 경청하며, '그랬구나, 정말 힘들었겠다'와 같이 감정을 반영해 주는 공감적 반응이 가장 큰 안정감을 준다."},{"topic":"재난 심리 안정","label":"재난 지역의 커뮤니티 모임","detail":"공통의 경험을 가진 사람들이 모여 서로의 어려움을 이야기하는 과정에서, '나만 겪는 일이 아니구나'라는 소속감과 안정감을 얻는다."},{"topic":"야생동물 접근 대비","label":"쓰레기통 주변의 동물 흔적","detail":"쓰레기통 주변에 특정 동물의 배설물이나 먹다 남긴 흔적이 자주 발견된다면, 해당 동물이 인간의 쓰레기를 주요 먹이원으로 인식하고 있음을 의미한다."},{"topic":"야생동물 접근 대비","label":"탐방로 주변의 훼손된 식물","detail":"탐방로를 벗어난 곳에서 식물이나 지형이 훼손된 흔적이 발견된다면, 동물이 인간의 통제 구역을 이동 통로로 이용하고 있음을 나타낸다."},{"topic":"물벼락 안전 수칙","label":"물놀이장 입구 안내 표지판","detail":"‘구명조끼 착용 필수’와 같은 문구는 안전 수칙이 법적 강제성을 갖는 지점임을 보여준다."},{"topic":"물벼락 안전 수칙","label":"물놀이 후 몸 떨림","detail":"물놀이를 마치고 옷을 입거나 휴식을 취할 때 몸이 떨리는 것은 저체온증의 초기 신호일 수 있다."},{"topic":"물벼락 안전 수칙","label":"물놀이 전 준비 운동 시간","detail":"공식적인 안전 수칙에서는 물에 들어가기 전 스트레칭 시간을 확보하도록 권고한다."},{"topic":"PvE 전략","label":"RPG 게임의 '최적 빌드' 공략","detail":"특정 캐릭터의 스킬 순서나 장비 세팅이 '이것이 가장 좋다'는 정형화된 가이드라인으로 존재한다."},{"topic":"PvE 전략","label":"MMORPG의 '레이드 공략 영상'","detail":"수많은 플레이어가 특정 패턴을 반복적으로 수행하며, 가장 효율적인 공략 순서와 타이밍을 공유한다."},{"topic":"방사능 노출","label":"병원 진료실의 X-ray 기기","detail":"필요한 부위만 촬영하고, 노출 시간을 최소화하려는 의료진의 노력이 방사선 안전의 실제 적용 사례이다."},{"topic":"방사능 노출","label":"지하철이나 건물 내부의 미세한 방사선 측정","detail":"일상생활 속에서도 배경 방사선이 존재하며, 이를 측정하는 장비가 상시적으로 활용된다."},{"topic":"플랫폼별 차이점","label":"앱스토어의 정책 변경","detail":"대형 플랫폼이 특정 결제 시스템을 강제하거나 수수료를 높일 때, 사용자들은 대체 결제 수단이나 외부 플랫폼을 찾게 된다."},{"topic":"플랫폼별 차이점","label":"특정 커뮤니티의 폐쇄성","detail":"한 플랫폼에서만 얻을 수 있는 고유한 정보나 관계성 때문에, 사용자들이 다른 플랫폼으로 이동하는 것을 꺼리게 된다."},{"topic":"핵심 공략 요소","label":"프로 경기 중 '정지된' 순간","detail":"격렬한 전투가 잠시 멈추고, 선수들이 다음 움직임을 예측하며 눈빛을 교환하는 순간은, 가장 치열한 '정보전'이 벌어지는 지점이다."},{"topic":"핵심 공략 요소","label":"패치 노트의 변화","detail":"특정 스킬의 너프나 버프가 발표되면, 기존의 '핵심 공략 요소'가 완전히 무효화되고 새로운 전략적 흐름이 형성된다."},{"topic":"경쟁 게임 트렌드","label":"크로스 플랫폼 게임의 인기","detail":"PC, 모바일, 콘솔 등 다양한 기기에서 끊김 없이 플레이가 가능하다는 점은, 유저의 생활 패턴과 게임 접근성을 극대화하는 트렌드이다."},{"topic":"경쟁 게임 트렌드","label":"IP 기반의 게임 출시","detail":"영화, 웹툰 등 이미 대중에게 인지된 IP를 활용하는 것은, 게임이 초기에 재미를 증명할 필요 없이 강력한 팬덤을 확보할 수 있게 한다."},{"topic":"MMORPG 시스템 이해","label":"길드 홍보 게시판","detail":"특정 콘텐츠(레이드, PvP)를 공략하기 위해 '최소 요구 레벨'나 '필수 장비 등급'을 명시하는 것은 시스템의 상호의존성을 보여준다."},{"topic":"MMORPG 시스템 이해","label":"경매장 거래 내역","detail":"특정 재화의 가격 변동을 통해, 해당 재화가 어떤 콘텐츠(생활/전투)에서 얼마나 많이 소비되는지 경제적 흐름을 파악할 수 있다."},{"topic":"배틀 로얄 전략","label":"e스포츠 경기 중의 팀원 간 대화","detail":"단순히 '어디에 있다'는 위치 공유를 넘어, '다음 구역으로 이동할 최적의 경로'를 논의하는 것이 전술적 사고의 증거이다."},{"topic":"배틀 로얄 전략","label":"게임 전술 분석 영상","detail":"승리한 팀의 플레이를 분석할 때, '어떤 아이템을 언제 사용했는지'의 시간적 흐름이 중요하게 다뤄진다."},{"topic":"스킨 디자인 트렌드","label":"콜라보레이션 상품","detail":"게임 캐릭터가 특정 영화나 브랜드의 의상, 소품을 입는 방식은, IP 간의 결합을 통해 새로운 미학적 가치를 창출하는 대표적인 사례이다."},{"topic":"스킨 디자인 트렌드","label":"시즌 패스 아이템","detail":"특정 기간 동안만 얻을 수 있는 한정판 스킨은, 사용자에게 희소성과 소속감을 부여하여 소비를 촉진하는 경제적 메커니즘을 보여준다."},{"topic":"유해물질 노출 대처","label":"산업 현장의 비상 샤워 시설","detail":"대부분의 샤워 시설은 단순히 물을 뿌리는 것을 넘어, 특정 화학물질에 대한 초기 세척 프로토콜을 갖추고 있다."},{"topic":"유해물질 노출 대처","label":"MSDS(물질안전보건자료) 게시","detail":"작업장마다 물질별 응급처치 방법, 노출 시 증상, 필요한 보호 장비 등이 구체적으로 명시되어 있다."},{"topic":"소방차 위치 파악","label":"교통 정보 앱의 경로 안내","detail":"현재 위치와 목적지 간의 최단 거리가 아닌, 실시간 교통 상황을 반영한 최적의 경로를 제시하는 것 자체가 위치 정보의 활용 예시이다."},{"topic":"소방차 위치 파악","label":"대형 건물 내 비상 안내 시스템","detail":"정전이나 통신 두절 상황에서도 비상 전력을 이용해 특정 구역의 위치와 대피 경로를 안내하는 시스템을 통해 위치 파악의 중요성을 보여준다."},{"topic":"자율방재 계획","label":"지역 공동체 훈련 프로그램","detail":"주민들이 모여 실제 재난 상황을 가정하고 역할을 분담하여 훈련하는 모습에서 자율방재의 실질적인 작동을 관찰할 수 있다."},{"topic":"자율방재 계획","label":"재난 발생 후 이웃 간의 도움","detail":"공식 구조대가 도착하기 전, 이웃들이 서로의 안전을 확인하고 기본적인 구호 활동을 펼치는 상황에서 자율방재의 필요성을 체감할 수 있다."},{"topic":"붕괴 현장 안전","label":"구조대원 보호 장비","detail":"헬멧이나 특수 장갑 등은 단순한 보호를 넘어, 현장의 위험 요소를 차단하고 작업 효율성을 유지하는 필수적인 장비로 활용된다."},{"topic":"붕괴 현장 안전","label":"구조 현장의 통제선","detail":"경계가 명확히 설정된 구역은 작업 반경을 제한하여, 추가적인 위험 요소가 현장으로 유입되는 것을 막는 역할을 한다."},{"topic":"응급 상황별 체크리스트","label":"재난 안내 방송","detail":"방송의 내용이 '무엇을 해야 하는지'보다 '어떤 순서로 해야 하는지'를 단계별로 안내할 때 체계적인 체크리스트의 중요성을 보여준다."},{"topic":"응급 상황별 체크리스트","label":"CPR 교육 현장","detail":"가슴 압박의 깊이, 속도, 횟수 등 구체적인 수치와 순서를 단계별로 반복 학습해야 정확한 처치가 가능하다."},{"topic":"직업 흥미 유형","label":"직업 상담 센터의 홍보 자료","detail":"다양한 흥미 유형(예: 예술형, 사회형)을 시각화하여 제시하며, 이를 통해 '나'를 정의하려는 시도가 보인다."},{"topic":"직업 흥미 유형","label":"취업 플랫폼의 추천 기능","detail":"사용자가 과거에 관심을 보였던 키워드나 활동 패턴을 분석하여, 유사한 흥미를 가질 만한 직무를 추천해 주는 방식으로 작동한다."},{"topic":"성격 유형 검사","label":"직장 내 팀 빌딩 활동","detail":"팀원들의 MBTI를 공유하며 서로의 강점과 약점을 인정하고 역할을 분담하는 과정에서 유형의 유용성을 체감한다."},{"topic":"성격 유형 검사","label":"데이트 코칭 프로그램","detail":"상대방의 성격 유형을 분석하여 '이런 유형과는 안 맞을 것 같다'는 식의 관계 예측에 활용하는 경우."},{"topic":"시간 관리 기법","label":"아침에 작성하는 To-Do 리스트","detail":"하루를 시작하며 가장 중요하다고 생각하는 3가지 항목을 적는 행위 자체가 그날의 핵심 우선순위를 강제로 설정하게 만든다."},{"topic":"시간 관리 기법","label":"회의 후의 '다음 행동(Next Action)' 기록","detail":"회의가 끝난 후 누가, 언제, 무엇을 할지 구체적인 행동 단위로 기록하는 과정이 모호한 논의를 실제 실행 계획으로 전환시킨다."},{"topic":"집중력 향상법","label":"업무용 메신저 알림","detail":"알림이 울릴 때마다 주의력이 분산되며, 원래 하던 작업으로 돌아가도 이전의 깊은 사고 상태를 회복하는 데 시간이 걸린다."},{"topic":"집중력 향상법","label":"장거리 운전 후의 졸음","detail":"지속적인 단조로운 활동은 뇌의 각성 상태를 떨어뜨려, 의도적인 휴식(스트레칭, 짧은 수면)이 필수적임을 보여준다."},{"topic":"공부 방법론","label":"스터디 플래너의 '진도' 항목","detail":"단순히 읽은 분량(양적 노력)을 기록하는 것에만 집중하는 것은, 실제로 이해하고 설명할 수 있는 깊이(질적 이해)를 측정하지 못한다."},{"topic":"공부 방법론","label":"토론이나 발표 준비 과정","detail":"자신이 알고 있는 지식을 상대방의 질문에 맞춰 즉각적으로 재구성하고 설명해야 할 때, 학습의 효과가 극대화된다."},{"topic":"효율적 메모법","label":"스터디 플래너의 복습 항목","detail":"단순히 '오늘 배운 것'을 적는 것보다, '어제 배운 것 중 헷갈리는 개념 3가지'를 지정하는 것이 복습의 초점을 명확히 한다."},{"topic":"효율적 메모법","label":"개념 간의 비교표 작성","detail":"A와 B의 차이점을 비교하는 표를 만들 때, 단순히 차이점만 나열하는 것이 아니라 '어떤 상황에서 A가 B를 대체하는가?'라는 관점으로 관계를 정의하는 것이 더 효과적이다."},{"topic":"브레인스토밍 기법","label":"회의록의 아이디어 섹션","detail":"회의록에 아이디어들이 무질서하게 나열되어 있다면, 이는 발산 단계는 성공했으나 구조화 단계가 필요함을 의미한다."},{"topic":"브레인스토밍 기법","label":"신제품 기획서의 초기 단계","detail":"초기 기획서에 다양한 관점의 아이디어가 혼재되어 있다면, 이는 브레인스토밍을 통해 폭넓은 가능성을 탐색했음을 보여준다."},{"topic":"정보 검색 전략","label":"뉴스 기사 제목의 과장성","detail":"자극적이고 감정적인 제목은 클릭을 유도하지만, 실제 기사 본문에서는 구체적인 데이터나 출처 제시가 부족하여 정보의 신뢰도를 의심하게 만든다."},{"topic":"정보 검색 전략","label":"검색 엔진의 '관련 검색어' 제시","detail":"사용자가 의도하지 않았던, 하지만 통계적으로 자주 검색되는 연관 키워드를 제시하여 검색 범위를 확장시키고 새로운 관점을 제공한다."},{"topic":"학습 주기 곡선","label":"플래시카드 앱 사용","detail":"단어 암기나 개념 복습 시, 앱이 자동으로 다음 복습 시점을 계산하여 제시하는 방식에서 간격 반복 학습의 원리를 체감할 수 있다."},{"topic":"학습 주기 곡선","label":"오래된 전공 지식 회상","detail":"오랜만에 접하는 전공 지식이나 외국어 문법을 떠올릴 때, 처음에는 막히지만 반복적인 시도 끝에 갑자기 기억이 떠오르는 경험을 할 수 있다."},{"topic":"최적 수면 패턴","label":"카페인 의존성","detail":"오전 중반이나 오후에 느끼는 급격한 피로감을 해소하기 위해 커피나 에너지 드링크에 의존하는 모습에서 수면 부족의 신호가 보인다."},{"topic":"최적 수면 패턴","label":"주말의 과도한 수면","detail":"평소보다 2~3시간 이상 늦잠을 자는 행동은 생체 시계의 혼란을 반영하며, 다음 주 초에 더 큰 피로를 느끼게 할 수 있다."},{"topic":"인지 부하 이론","label":"복잡한 매뉴얼 읽기","detail":"너무 많은 기능과 절차가 한 페이지에 나열되어 있으면, 독자는 어디서부터 읽어야 할지 몰라 압도당하고 중요한 정보를 놓치게 된다."},{"topic":"인지 부하 이론","label":"긴 강의 듣기","detail":"강의가 지나치게 길고 내용 전환이 빠르면, 청자는 중간에 집중력을 잃거나 앞 내용을 기억하지 못하는 '흐름 끊김'을 경험한다."},{"topic":"인지 편향 사례","label":"뉴스 댓글 창","detail":"자신이 지지하는 주장에 대한 반대 의견을 보면, 그 논리적 오류를 찾아내기보다 감정적으로 공격하거나 무시하는 경향이 강하게 나타난다."},{"topic":"인지 편향 사례","label":"새로운 제품의 초기 가격 책정","detail":"처음 제시된 가격(앵커)이 소비자의 기대치를 설정하여, 이후 제시되는 할인 가격이나 다른 제품의 가격을 판단하는 기준점 역할을 한다."},{"topic":"심리학 용어","label":"뉴스 기사 소비 패턴","detail":"자신이 지지하는 정치적 성향의 기사만 찾아 읽고, 반대 의견의 기사는 출처가 불분명하다고 치부하는 경향이 나타난다."},{"topic":"심리학 용어","label":"토론이나 회의 자리","detail":"자신의 의견을 지지하는 동료의 발언에만 집중하고, 반대 의견을 제시하는 사람의 논리적 허점을 찾으려 애쓰는 모습이 관찰된다."},{"topic":"사회 심리 현상","label":"SNS의 좋아요/조회수","detail":"게시물에 달린 높은 좋아요 수나 조회수는 내용의 질적 가치보다 '많은 사람이 관심을 가졌다'는 사회적 증거로 작용하여, 무분별한 확산을 유도한다."},{"topic":"사회 심리 현상","label":"유행하는 챌린지 참여","detail":"특정 챌린지에 참여하는 것은 재미나 의미 부여를 넘어, '나도 이 집단에 속해 있다'는 소속감을 확인하고 싶어 하는 심리적 욕구의 발현이다."},{"topic":"관계 패턴 분석","label":"SNS의 '친구 추천' 기능","detail":"사용자가 직접 연결하지 않았지만, 공통의 친구나 관심사를 통해 연결될 가능성이 높은 노드를 제시함으로써 잠재적 관계 패턴을 활용한다."},{"topic":"관계 패턴 분석","label":"신제품의 시장 확산 경로","detail":"초기 도입 사용자(Early Adopter)를 중심으로 제품이 특정 커뮤니티를 따라 확산되는 패턴을 분석하여 마케팅 전략을 수립한다."},{"topic":"커뮤니케이션 스킬","label":"회의 중 메모하는 행위","detail":"단순히 기록하는 것을 넘어, 상대방의 핵심 주장을 요약하거나 질문을 준비하는 과정 자체가 경청의 적극적인 증거가 된다."},{"topic":"커뮤니케이션 스킬","label":"대화 후 '요약해서 말씀드리자면'이라는 표현","detail":"상대방의 말을 다시 한번 정리하여 되돌려주는 행위는, 자신이 제대로 이해했는지 확인하는 동시에 상대방에게 '내가 당신을 듣고 있다'는 확신을 준다."},{"topic":"갈등 해결 방식","label":"회의록의 '합의 사항' 섹션","detail":"갈등 해결의 결과물이 명시적으로 기록되는 부분으로, 누가 어떤 의견을 포기하고 어떤 원칙에 따라 결정했는지 그 과정의 흔적이 남아있다."},{"topic":"갈등 해결 방식","label":"조정위원회나 중재 기관의 존재","detail":"사적인 영역에서 해결하기 어려운 갈등이 법적, 제도적 장치를 통해 공적으로 개입되어 해결되는 모습을 통해 그 필요성을 체감할 수 있다."},{"topic":"의사 결정 트리","label":"챗봇의 대화 흐름 설계","detail":"사용자의 질문 의도(Intent)를 파악하고, 그 의도에 따라 미리 정의된 질문과 답변의 경로를 순차적으로 안내하는 구조가 의사 결정 트리의 원리와 유사하다."},{"topic":"의사 결정 트리","label":"복잡한 업무 프로세스 매뉴얼","detail":"특정 상황(조건)이 발생했을 때, '만약 A라면 B를 하고, 그렇지 않다면 C를 하라'와 같은 조건문(If-Else)의 연속적인 흐름으로 설계되어 있다."},{"topic":"문제 해결 프로세스","label":"신제품 기획 회의","detail":"고객의 불만(증상)을 듣는 것에서 멈추지 않고, 그 불만이 발생하는 근본적인 사용 환경이나 시스템의 결함을 파고들어 제품의 핵심 기능을 재설계하는 과정에서 이 프로세스가 작동한다."},{"topic":"문제 해결 프로세스","label":"개인적인 갈등 해결","detail":"단순히 '누가 잘못했는지'를 따지는 감정적 논쟁을 넘어, '어떤 규칙이나 시스템이 이 갈등을 유발했는지'를 분석하여 구조적인 해결책을 찾는 과정에서 활용된다."},{"topic":"게이미피케이션 원리","label":"운동 앱의 연속 기록","detail":"달리기 기록을 연속으로 갱신하거나 '연속 기록 유지' 배지를 받으려는 심리가, 운동 자체의 즐거움보다 더 큰 동기 부여가 되기도 한다."},{"topic":"게이미피케이션 원리","label":"업무용 프로젝트 관리 툴","detail":"업무 할당량이나 마감 기한을 '레벨'이나 '퀘스트' 형태로 시각화하여, 업무를 게임처럼 수행하도록 유도하는 경우가 늘고 있다."},{"topic":"파밍 개념","label":"게임 공략 영상의 편집 방식","detail":"효율적인 파밍 루트를 보여줄 때, 불필요한 전투 장면을 과감히 편집하고 핵심 자원 획득 지점만 강조하는 방식으로 나타난다."},{"topic":"파밍 개념","label":"아이템 거래소의 가격 변동","detail":"특정 파밍 콘텐츠에서 대량으로 획득되는 재료의 가격이 급격히 변동하는 것은, 해당 자원의 공급 과잉 또는 부족을 보여주는 경제적 신호이다."},{"topic":"UI/UX 디자인 원리","label":"복잡한 공공기관 웹사이트","detail":"필요한 정보가 산재되어 있고, 메뉴 구조가 비직관적이어서 사용자가 원하는 정보를 찾기 위해 여러 페이지를 헤매게 만드는 경우."},{"topic":"UI/UX 디자인 원리","label":"새로운 앱의 온보딩 과정","detail":"앱을 처음 열었을 때, 핵심 기능 사용법을 단계별로 친절하게 안내해주어 사용자가 기능을 빠르게 습득하도록 돕는 과정."},{"topic":"세계관 설정 방법","label":"게임의 튜토리얼(Tutorial)","detail":"게임 초반에 시스템의 작동 방식(규칙)을 강제로 학습시키는 과정은, 독자가 세계관의 기본 규칙을 이해하도록 돕는 역할을 한다."},{"topic":"세계관 설정 방법","label":"역사 다큐멘터리","detail":"특정 시대의 사회적, 정치적 제약(규칙)을 보여줌으로써, 그 시대 사람들의 선택과 행동에 필연적인 개연성을 부여한다."},{"topic":"경련성 발작 대처","label":"가족의 응급 키트","detail":"발작이 잦은 가족을 위해 안전한 환경 조성 물품(예: 충격 흡수 매트, 안전 가드)을 미리 준비해 두는 모습에서 예방적 관리가 중요하다는 것을 알 수 있다."},{"topic":"경련성 발작 대처","label":"응급 상황 안내 표지판","detail":"공공장소에 '발작 발생 시 대처 요령' 등의 안내가 붙어 있는 경우, 사회적 인식과 교육의 필요성이 높아지고 있음을 보여준다."},{"topic":"외상환자 이송 요령","label":"구급차 내부의 장비 배치","detail":"기도 확보를 위한 기도기(Airway adjunct)와 쇼크 관리를 위한 수액 백이 가장 접근하기 쉬운 위치에 배치되어 있다."},{"topic":"외상환자 이송 요령","label":"외상 환자 이송 전 보호자들의 행동","detail":"보호자들이 환자의 부상 부위를 만지거나 움직이게 하려는 경향을 보여, 의료진의 경추 고정 지시가 필요하다."},{"topic":"위험 지역 안전 수칙","label":"공공장소의 비상구 표지판","detail":"위험 상황 발생 시 가장 먼저 시선이 머무는 곳은 '탈출'이라는 목적을 시각적으로 안내하는 표지판이다."},{"topic":"위험 지역 안전 수칙","label":"산업 현장의 안전모 및 안전띠","detail":"위험성이 높은 작업 환경에서는 개인의 생명을 보호하는 장비 착용이 일상적인 관행으로 자리 잡는다."},{"topic":"리그 시스템 원리","label":"리그 순위표의 변동","detail":"한 경기의 승패가 순위표의 상위권 팀 간 간격을 급격하게 좁히거나 벌리는 모습에서 시스템의 민감도를 체감할 수 있다."},{"topic":"리그 시스템 원리","label":"플레이오프 대진표 발표","detail":"정규 시즌 순위가 단순히 점수 순이 아니라, 특정 기준(예: 지역, 상위 N위)에 따라 그룹화되는 것을 통해 구조적 제한을 알 수 있다."},{"topic":"로딩 화면 디자인","label":"대형 웹사이트의 '스토리텔링' 로딩","detail":"단순한 로딩 바 대신, 서비스의 배경 이야기나 개발 과정 등을 애니메이션으로 보여주며 사용자의 흥미를 유발하는 경우."},{"topic":"로딩 화면 디자인","label":"게임의 '컷신' 또는 '전환 장면'","detail":"다음 스테이지로 넘어가기 전, 캐릭터의 대화나 배경 전환을 시각적으로 보여주어 다음 콘텐츠에 대한 몰입도를 높이는 경우."},{"topic":"화재 감지기","label":"소화전함 근처의 경보음","detail":"경보음이 울릴 때, 단순히 '화재'라는 메시지 외에 '몇 층 몇 호'와 같은 구체적인 위치 정보가 함께 전달된다."},{"topic":"화재 감지기","label":"감지기 청소 알림 스티커","detail":"감지기 주변에 먼지나 오염으로 인해 민감도가 떨어질 수 있다는 경고 문구가 붙어 있는 것을 볼 수 있다."},{"topic":"야간 운전 주의","label":"차량 내 졸음 방지 시스템 경고","detail":"운전자가 일정 시간 동안 주의력이 떨어지거나 졸음 징후를 보이면 차량이 경고음이나 진동을 발생시켜 운전자를 자극한다."},{"topic":"야간 운전 주의","label":"야간 운전 시 밝은 헤드라이트의 과부하","detail":"맞은편 차량의 강한 헤드라이트를 마주칠 때 일시적으로 눈이 부시거나 시야가 제한되는 현상이 관찰된다."},{"topic":"방범창 설치","label":"주차장 입구의 쇠창살","detail":"차량이나 사람이 무단으로 진입하는 것을 막기 위해 설치된 물리적 장벽은, 해당 공간의 접근 권한을 시각적으로 명확히 구분해준다."},{"topic":"방범창 설치","label":"1층 창문의 강화 유리","detail":"깨지기 어려운 특수 유리를 사용한 창문은, 침입자가 창문을 파손하는 데 필요한 시간과 도구를 증가시켜 범죄 시도를 주저하게 만든다."},{"topic":"경찰 신고 절차","label":"112 상담원과의 통화","detail":"상담원이 '육하원칙(누가, 언제, 어디서, 무엇을, 어떻게, 왜)'에 따라 질문을 반복하는 과정 자체가, 신고자가 정보의 누락을 스스로 인지하게 만드는 구조적 장치이다."},{"topic":"경찰 신고 절차","label":"현장 출동 차량의 도착","detail":"경찰차의 사이렌 소리나 출동 차량의 존재는 신고자에게 심리적 안정감과 동시에, 사건이 공식적으로 처리되고 있다는 인식을 심어준다."},{"topic":"주차장 안전거리","label":"주차장 통로의 장애물","detail":"자전거, 쓰레기, 혹은 임시로 놓인 물건 등으로 인해 주차장 통로가 좁아지거나 막혀 있는 경우, 안전거리 확보가 불가능한 상황을 보여준다."},{"topic":"주차장 안전거리","label":"화재 발생 차량의 배치","detail":"주차된 차량들이 벽이나 기둥을 따라 일렬로 배치되어 있어, 화재 시 연기가 한 방향으로만 빠져나갈 위험을 보여준다."},{"topic":"버그 및 핵 방지","label":"게임 접속 시의 경고창","detail":"접속 시 '안티 치트 시스템 업데이트 필요' 또는 '비정상적인 활동 감지'와 같은 메시지는 시스템이 작동하고 있음을 사용자에게 명시적으로 알리는 신호이다."},{"topic":"버그 및 핵 방지","label":"패치 노트의 '버그 수정' 항목","detail":"특정 버그가 수정되었다는 공지 자체가, 그 버그가 과거에 게임 플레이의 핵심적인 취약점이었음을 간접적으로 증명한다."},{"topic":"게임 UX/UI 원칙","label":"게임 내 튜토리얼 과정","detail":"초보자에게는 모든 기능을 단계별로 강제 학습시키지만, 숙련자에게는 해당 과정을 건너뛰거나 축약하여 보여주는 차별화된 UX가 적용된다."},{"topic":"게임 UX/UI 원칙","label":"아이템 획득 애니메이션","detail":"아이템을 얻거나 스킬을 성공적으로 사용했을 때의 시각적/청각적 효과는 단순히 '보상'을 넘어, 플레이어의 성취감을 극대화하는 피드백 장치 역할을 한다."},{"topic":"경쟁 게임 디자인","label":"패치 노트의 '밸런스 조정'","detail":"개발사가 특정 캐릭터나 무기의 성능 수치를 변경하는 것은, 현재 메타가 너무 한쪽으로 치우치거나 특정 전략이 과도하게 강력해졌음을 의미한다."}]